{"errno": 0, "totalPage": 4, "replies": [{"avatar": "https://i1.hdslb.com/bfs/face/62237b5dbdf0946c10952a9c7bf62c90170db206.jpg", "uname": "khraka", "current_level": 4, "vipStatus": 1, "is_senior_member": 0, "message": "看过少歌剧场版的话更绷不住", "ctime": "2023-09-29 16:50:30", "like": 1}, {"avatar": "http://i2.hdslb.com/bfs/face/a1ad63e76a560f055decff0c5904510ffe6f75ee.jpg", "uname": "我永远喜欢斗和キセキ", "current_level": 6, "vipStatus": 0, "is_senior_member": 0, "message": "“观众席原来这么近吗”<br>“soyo”", "ctime": "2023-09-29 20:12:55", "like": 6}, {"avatar": "https://i1.hdslb.com/bfs/face/2009b6d3f43b2553b986627651df881fa3c9ccf0.jpg", "uname": "長崎そよ_official", "current_level": 6, "vipStatus": 1, "is_senior_member": 0, "message": "sodayo", "ctime": "2023-09-29 23:30:16", "like": 0}, {"avatar": "https://i2.hdslb.com/bfs/face/69bed67ff2ec9a0d747c78b05166e595beeb5636.jpg", "uname": "热的太阳", "current_level": 5, "vipStatus": 1, "is_senior_member": 0, "message": "回复 @khraka :coco好像才刚看过少歌剧场版，说不定真为这个笑过", "ctime": "2023-09-29 23:58:14", "like": 0}]}