{"errno": 0, "totalPage": 4, "replies": [{"avatar": "https://i1.hdslb.com/bfs/face/ed47fdebe4ce560ad780872ff25a5347577c0193.jpg", "uname": "T1anwah2", "current_level": 6, "vipStatus": 1, "is_senior_member": 0, "message": "什么列文虎克", "ctime": "2023-08-28 02:50:38", "like": 2}, {"avatar": "https://i0.hdslb.com/bfs/face/c415b55cd728e81d102bea86f58350d4f3637c21.jpg", "uname": "星詠みKell_Yin", "current_level": 5, "vipStatus": 1, "is_senior_member": 0, "message": "这能确定是同一个人嘛？[小A和小B_喝茶]", "ctime": "2023-08-28 04:35:09", "like": 1}, {"avatar": "https://i1.hdslb.com/bfs/face/d71e2997a5eba04c85c95133cd198b408f627345.jpg", "uname": "音无结弦丷", "current_level": 6, "vipStatus": 1, "is_senior_member": 1, "message": "这个目前还不确定，互相之间没连起来。", "ctime": "2023-08-28 10:22:58", "like": 6}, {"avatar": "https://i2.hdslb.com/bfs/face/f822368771869319791987d26e259b5de0d14321.jpg", "uname": "小糸灯子", "current_level": 5, "vipStatus": 0, "is_senior_member": 0, "message": "这也不一定吧", "ctime": "2023-08-28 14:24:09", "like": 0}]}