{"errno": 0, "totalPage": 248, "replies": [{"avatar": "/static/pic/i1.hdslb.com/bfs/face/b2b71f12432e8a8f577c79eeab426ec809dd3751.jpg", "pendant": "", "uname": "墨影成凉", "current_level": 5, "vipStatus": 0, "is_senior_member": 0, "user_sailing": null, "message": "之前的bangdream动画有什么好看的吗？", "ctime": "2023-09-17 12:30:08", "like": 0, "replies": [{"avatar": "/static/pic/i0.hdslb.com/bfs/face/fca1ac76b65a3d1eacd497b2bafa5f5b67f1ea1a.jpg", "uname": "喜多依库哟", "current_level": 6, "vipStatus": 1, "is_senior_member": 1, "message": "可以去看看第二季第四集（可以直接看，公认神回），看看同一个世界观下的作品画风差距是多么的大", "ctime": "2023-09-17 13:12:39", "like": 3}, {"avatar": "/static/pic/i0.hdslb.com/bfs/face/5da5fa8e58f44f7aabd01fc325b19d3b3f6248f7.jpg", "uname": "小林家的妹抖狐", "current_level": 6, "vipStatus": 1, "is_senior_member": 0, "message": "回复 @丸先生43 :yysy，我mmr，很喜欢二三季，也对MyGO能创作出如此大胆地剧本感觉很新奇，以往我是很抗拒看这种扭曲番，终将我都没看下去，但MyGO我看的好爽[笑哭]", "ctime": "2023-09-17 17:30:28", "like": 1}, {"avatar": "/static/pic/i1.hdslb.com/bfs/face/b2b71f12432e8a8f577c79eeab426ec809dd3751.jpg", "uname": "墨影成凉", "current_level": 5, "vipStatus": 0, "is_senior_member": 0, "message": "回复 @喜多依库哟 :好的，谢谢", "ctime": "2023-09-24 15:44:08", "like": 0}], "sub_reply_entry_text": "共16条回复"}, {"avatar": "/static/pic/i1.hdslb.com/bfs/face/3b0515fba6079f1ef62a60dee2dfde9a8e811f18.jpg", "pendant": "/static/pic/i1.hdslb.com/bfs/garb/item/82898a454a648be3a05e57d5c6cca1f81f95eb15.png", "uname": "没有雪乃只有问题", "current_level": 6, "vipStatus": 0, "is_senior_member": 0, "user_sailing": {"pendant": {"id": 32948, "name": "贝拉kira", "image": "https://i0.hdslb.com/bfs/garb/item/82898a454a648be3a05e57d5c6cca1f81f95eb15.png", "jump_url": "", "type": "suit", "image_enhance": "https://i0.hdslb.com/bfs/garb/item/82898a454a648be3a05e57d5c6cca1f81f95eb15.png", "image_enhance_frame": ""}, "cardbg": {"id": 37639, "name": "贝拉个性装扮2.0", "image": "https://i0.hdslb.com/bfs/garb/item/b82d6d89aee54def6b84752271bd3d428da2a32f.png", "jump_url": "https://www.bilibili.com/h5/mall/equity-link/home?navhide=1&item_id=37639&part=card_bg&f_source=garb&from=reply&vmid=93733474", "fan": {"is_fan": 1, "number": 3665, "color": "#c86161", "name": "贝拉个性装扮2.0", "num_desc": "003665"}, "type": "suit"}, "cardbg_with_focus": null}, "message": "海玲声音是真好听[给心心][给心心]", "ctime": "2023-09-17 13:07:34", "like": 0, "replies": [], "sub_reply_entry_text": ""}, {"avatar": "/static/pic/i1.hdslb.com/bfs/face/d47fa0975d03bcf00b1b3f3bd4d94618785c1a68.jpg", "pendant": "", "uname": "binchon", "current_level": 5, "vipStatus": 1, "is_senior_member": 0, "user_sailing": null, "message": "MUJICA是继RAS后心动的乐队。", "ctime": "2023-09-17 14:07:44", "like": 0, "replies": [], "sub_reply_entry_text": ""}, {"avatar": "/static/pic/i2.hdslb.com/bfs/face/6eb9af5da3c9c012c5c47f80d03f50e01e98bc2d.jpg", "pendant": "", "uname": "混言小R", "current_level": 6, "vipStatus": 0, "is_senior_member": 1, "user_sailing": null, "message": "我已经迫不及待看到前银河舰队和现银河舰队对创了[喜欢]", "ctime": "2023-09-17 14:01:23", "like": 0, "replies": [], "sub_reply_entry_text": ""}, {"avatar": "/static/pic/i0.hdslb.com/bfs/face/eab3c380c03300ed26c8ce8dadf65fc50a15bcfc.jpg", "pendant": "", "uname": "豊川祥子_哭哭版", "current_level": 6, "vipStatus": 1, "is_senior_member": 0, "user_sailing": null, "message": "[小电视_我好兴奋]24年一月份能看到祥子哭哭吗？", "ctime": "2023-09-17 12:30:07", "like": 0, "replies": [], "sub_reply_entry_text": ""}, {"avatar": "/static/pic/i0.hdslb.com/bfs/face/49d58ebea0878fbfd1d40efd27e0811ea2748b00.jpg", "pendant": "", "uname": "无尽之渊2", "current_level": 6, "vipStatus": 1, "is_senior_member": 0, "user_sailing": null, "message": "和解之后的关系，感觉有点乱，只有十一个人开音趴（甜甜圈女士+10人），大家自己找喜欢的人做喜欢的事，soyo和初华找祥子，灯找爱音和祥子，睦找soyo，立希找灯，祥子躺着就好，毕竟人有点多，这样大家都幸福的世界达成了[doge]", "ctime": "2023-09-17 12:56:29", "like": 0, "replies": [], "sub_reply_entry_text": ""}, {"avatar": "/static/pic/i2.hdslb.com/bfs/face/dad3f4d54a1972dec823218491f927c59987498d.jpg", "pendant": "", "uname": "Heals_216", "current_level": 5, "vipStatus": 0, "is_senior_member": 0, "user_sailing": null, "message": "太强了这一集，mygo不要联系了，我怕母鸡卡误会[喜欢]", "ctime": "2023-09-17 12:27:10", "like": 0, "replies": [], "sub_reply_entry_text": ""}, {"avatar": "/static/pic/i1.hdslb.com/bfs/face/c4f095830a8fd219f72dc8e9b219e9d61f660788.jpg", "pendant": "/static/pic/i1.hdslb.com/bfs/face/d3587e6f3b534499fc08a71296bafa74a159fa33.png", "uname": "O茵蒂克丝O", "current_level": 6, "vipStatus": 1, "is_senior_member": 1, "user_sailing": {"pendant": {"id": 258, "name": "梦100", "image": "https://i0.hdslb.com/bfs/face/d3587e6f3b534499fc08a71296bafa74a159fa33.png", "jump_url": "", "type": "vip", "image_enhance": "https://i0.hdslb.com/bfs/face/d3587e6f3b534499fc08a71296bafa74a159fa33.png", "image_enhance_frame": ""}, "cardbg": {"id": 2476, "name": "神楽Mea", "image": "https://i0.hdslb.com/bfs/garb/item/f134230db5a35b00156a114eedd6c245f9151e35.png", "jump_url": "https://www.bilibili.com/h5/mall/equity-link/home?navhide=1&item_id=2476&part=card_bg&f_source=garb&from=reply&vmid=46871224", "fan": {"is_fan": 1, "number": 29127, "color": "#80cedd", "name": "神楽Mea", "num_desc": "029127"}, "type": "suit"}, "cardbg_with_focus": null}, "message": "我想我大概……一辈子都忘不了MyGO吧", "ctime": "2023-09-17 13:08:30", "like": 0, "replies": [], "sub_reply_entry_text": ""}, {"avatar": "/static/pic/i1.hdslb.com/bfs/face/a8b87dd48ee30ec21537761bb8903f2a942426ae.jpg", "pendant": "", "uname": "pccongroo", "current_level": 5, "vipStatus": 1, "is_senior_member": 0, "user_sailing": null, "message": "没人说祥子是对的（好吧可能确实有人），但我还是喜欢祥子", "ctime": "2023-09-17 14:33:29", "like": 0, "replies": [], "sub_reply_entry_text": ""}, {"avatar": "/static/pic/i0.hdslb.com/bfs/face/a5dfcef25529e9a0d10f2324dd313509090e3430.jpg", "pendant": "", "uname": "堕氏", "current_level": 5, "vipStatus": 0, "is_senior_member": 0, "user_sailing": null, "message": "为什么播放量还没破100w", "ctime": "2023-09-17 16:32:46", "like": 0, "replies": [], "sub_reply_entry_text": ""}, {"avatar": "/static/pic/i0.hdslb.com/bfs/face/2519d825fec45b6e3620933a83e4f586aa03d5a7.jpg", "pendant": "/static/pic/i0.hdslb.com/bfs/garb/item/21e72a6812371baf9729dba58864780d33deb557.png", "uname": "姬宝的24k纯金萨摩耶", "current_level": 5, "vipStatus": 1, "is_senior_member": 0, "user_sailing": {"pendant": {"id": 5393, "name": "雫るる", "image": "https://i0.hdslb.com/bfs/garb/item/21e72a6812371baf9729dba58864780d33deb557.png", "jump_url": "", "type": "suit", "image_enhance": "https://i0.hdslb.com/bfs/garb/item/21e72a6812371baf9729dba58864780d33deb557.png", "image_enhance_frame": ""}, "cardbg": {"id": 33366, "name": "未来有你5周年", "image": "https://i0.hdslb.com/bfs/garb/item/716c23351ff21510dddc61fa17b898ef51eaed05.png", "jump_url": "https://www.bilibili.com/h5/mall/equity-link/home?navhide=1&item_id=33366&part=card_bg&f_source=garb&from=reply&vmid=629860638", "fan": {"is_fan": 1, "number": 45530, "color": "#4e7f97", "name": "未来有你5周年", "num_desc": "045530"}, "type": "suit"}, "cardbg_with_focus": null}, "message": "mujica看着是祥子和初华双c", "ctime": "2023-09-17 14:01:33", "like": 0, "replies": [], "sub_reply_entry_text": ""}, {"avatar": "/static/pic/i1.hdslb.com/bfs/face/e0fcaa2bc5eef30a67b34d77274f7ed8a2e1e623.jpg", "pendant": "/static/pic/i1.hdslb.com/bfs/face/17cd0b10bc8818a5338e515a340ec25bc0347d8c.png", "uname": "兔田Pekora", "current_level": 6, "vipStatus": 1, "is_senior_member": 1, "user_sailing": {"pendant": {"id": 352, "name": "不吉波普不笑", "image": "https://i0.hdslb.com/bfs/face/17cd0b10bc8818a5338e515a340ec25bc0347d8c.png", "jump_url": "", "type": "vip", "image_enhance": "https://i0.hdslb.com/bfs/face/17cd0b10bc8818a5338e515a340ec25bc0347d8c.png", "image_enhance_frame": ""}, "cardbg": {"id": 3776, "name": "神乐七奈", "image": "https://i0.hdslb.com/bfs/garb/item/e02c64f6ecdef7a6bb44834ab96ef6ad34e467b8.png", "jump_url": "https://www.bilibili.com/h5/mall/equity-link/home?navhide=1&item_id=3776&part=card_bg&f_source=garb&from=reply&vmid=25355464", "fan": {"is_fan": 1, "number": 10073, "color": "#ff669c", "name": "神乐七奈", "num_desc": "010073"}, "type": "suit"}, "cardbg_with_focus": null}, "message": "就这么没了？", "ctime": "2023-09-17 16:00:30", "like": 0, "replies": [], "sub_reply_entry_text": ""}, {"avatar": "/static/pic/i1.hdslb.com/bfs/face/9e98a518f194943fe43eff081f8076f9d4be6420.jpg", "pendant": "", "uname": "バ音河", "current_level": 6, "vipStatus": 1, "is_senior_member": 0, "user_sailing": null, "message": "我想我大概……一辈子也忘不了MyGO!!!!!吧！", "ctime": "2023-09-17 16:23:17", "like": 0, "replies": [], "sub_reply_entry_text": ""}, {"avatar": "/static/pic/i2.hdslb.com/bfs/face/bd1fb7a99481c750120b42998677b31ccadb0d2d.jpg", "pendant": "", "uname": "没有硬币就讨饭", "current_level": 6, "vipStatus": 1, "is_senior_member": 0, "user_sailing": null, "message": "我想我大概……一辈子都忘不了MyGO!!!!!吧", "ctime": "2023-09-17 16:55:12", "like": 0, "replies": [], "sub_reply_entry_text": ""}, {"avatar": "/static/pic/i1.hdslb.com/bfs/face/938dbbf49797d73471152e22fa3d75a9f3c6401e.jpg", "pendant": "", "uname": "惊破秋窗秋梦续", "current_level": 6, "vipStatus": 1, "is_senior_member": 0, "user_sailing": null, "message": "我想我大概……一辈子都忘不了MyGO吧", "ctime": "2023-09-17 16:22:29", "like": 0, "replies": [], "sub_reply_entry_text": ""}, {"avatar": "/static/pic/i2.hdslb.com/bfs/face/e193f02ffdfd39787d94c5ad3a1ba77720a252b4.jpg", "pendant": "", "uname": "HHingKing大亨", "current_level": 5, "vipStatus": 1, "is_senior_member": 0, "user_sailing": null, "message": "我想我大概……一辈子都忘不了MyGO吧", "ctime": "2023-09-17 16:41:29", "like": 0, "replies": [], "sub_reply_entry_text": ""}, {"avatar": "/static/pic/i1.hdslb.com/bfs/face/7f5d6c6d71dc3efe9b5824c2984f5a2eb9dfba6a.jpg", "pendant": "", "uname": "NullSilence", "current_level": 6, "vipStatus": 0, "is_senior_member": 0, "user_sailing": null, "message": "我想我大概……一辈子都忘不了MyGO吧", "ctime": "2023-09-17 16:22:37", "like": 0, "replies": [], "sub_reply_entry_text": ""}, {"avatar": "/static/pic/i2.hdslb.com/bfs/face/ee6eeab24aa108f935c6fc33792429bd4e8c434e.jpg", "pendant": "/static/pic/i2.hdslb.com/bfs/garb/item/92d63a9014d4f0b2cefaef64f757162f750c7ad0.png", "uname": "正道不明", "current_level": 6, "vipStatus": 1, "is_senior_member": 0, "user_sailing": {"pendant": {"id": 6053, "name": "星尘", "image": "https://i0.hdslb.com/bfs/garb/item/92d63a9014d4f0b2cefaef64f757162f750c7ad0.png", "jump_url": "", "type": "suit", "image_enhance": "https://i0.hdslb.com/bfs/garb/item/92d63a9014d4f0b2cefaef64f757162f750c7ad0.png", "image_enhance_frame": ""}, "cardbg": {"id": 1680280626001, "name": "幻想乡的日常 第1弹", "image": "https://i0.hdslb.com/bfs/baselabs/op/61741f51abad0e44e1e6b97cfed3867650e0f22486b375c99de67af1a8d5029d.png", "jump_url": "https://www.bilibili.com/h5/mall/equity-link/home?navhide=1&item_id=1680280626001&part=card_bg&f_source=garb&from=reply&vmid=29597423", "fan": {"is_fan": 1, "number": 13201, "color": "#EC3D3D", "name": "幻想乡的日常 第1弹", "num_desc": "013201"}, "type": "suit"}, "cardbg_with_focus": null}, "message": "我想我大概……一辈子都忘不了MyGO吧", "ctime": "2023-09-17 12:29:35", "like": 0, "replies": [], "sub_reply_entry_text": ""}, {"avatar": "/static/pic/i0.hdslb.com/bfs/face/member/noface.jpg", "pendant": "", "uname": "彳亍髑髅", "current_level": 6, "vipStatus": 1, "is_senior_member": 0, "user_sailing": {"pendant": null, "cardbg": {"id": 34075, "name": "崩坏3·雷鸣彻空", "image": "https://i0.hdslb.com/bfs/garb/item/b5400ce0a12c60260a7c23fe74b05d328dc14a15.png", "jump_url": "https://www.bilibili.com/h5/mall/equity-link/home?navhide=1&item_id=34075&part=card_bg&f_source=garb&from=reply&vmid=171335044", "fan": {"is_fan": 1, "number": 38935, "color": "#ea3556", "name": "崩坏3·雷鸣彻空", "num_desc": "038935"}, "type": "suit"}, "cardbg_with_focus": null}, "message": "我想我大概……一辈子也忘不了MyGO!!!!!吧！", "ctime": "2023-09-17 16:48:25", "like": 0, "replies": [], "sub_reply_entry_text": ""}, {"avatar": "/static/pic/i0.hdslb.com/bfs/face/568c7a50bb47c5c249670add7728c7e67edc7244.jpg", "pendant": "", "uname": "秩序与混沌的火枪手", "current_level": 6, "vipStatus": 0, "is_senior_member": 1, "user_sailing": null, "message": "我想我大概……一辈子都忘不了MyGO吧", "ctime": "2023-09-17 14:51:45", "like": 0, "replies": [], "sub_reply_entry_text": ""}]}