{"errno": 0, "totalPage": 25, "replies": [{"avatar": "/static/pic/i1.hdslb.com/bfs/face/40afccd80425fd4c427dee09b915b99456872741.jpg", "pendant": "/static/pic/i1.hdslb.com/bfs/garb/item/d8caba83a6c5d917c15436c0bead848e41a5d0b5.png", "uname": "-喵喵长颈鹿-", "current_level": 6, "vipStatus": 0, "is_senior_member": 0, "user_sailing": {"id": 2446, "name": "湊-阿库娅", "image": "/static/pic/i0.hdslb.com/bfs/garb/item/91ff2f27b1f7c1ed2515f828c0663c779b6026c7.png", "jump_url": "https://www.bilibili.com/h5/mall/equity-link/home?navhide=1&item_id=2446&part=card_bg&f_source=garb&from=reply&vmid=348821209", "fan": {"is_fan": 1, "number": 3841, "color": "#f092da", "name": "湊-阿库娅", "num_desc": "003841"}, "type": "suit"}, "message": "真的好喜欢有祥子钢琴的春日影[保卫萝卜_哭哭]", "ctime": "2023-08-12 03:50:36", "like": 5, "replies": [], "sub_reply_entry_text": "", "pictures": []}, {"avatar": "/static/pic/i0.hdslb.com/bfs/face/3a6cc53a8fb291ef90080e72e80e37af05727f45.jpg", "pendant": "/static/pic/i0.hdslb.com/bfs/garb/item/3b7190a64fa613ac85a91d4d1f117a2cd4dfdb3b.png", "uname": "冈山桃太郎", "current_level": 6, "vipStatus": 1, "is_senior_member": 0, "user_sailing": {"id": 6443, "name": "阿梓", "image": "/static/pic/i0.hdslb.com/bfs/garb/item/fc343a588ed5129798968ff70f1d776e5d7148b3.png", "jump_url": "https://www.bilibili.com/h5/mall/equity-link/home?navhide=1&item_id=6443&part=card_bg&f_source=garb&from=reply&vmid=56309004", "fan": {"is_fan": 1, "number": 31490, "color": "#958dff", "name": "阿梓从小就很可爱", "num_desc": "031490"}, "type": "suit"}, "message": "第三集实在太青春疼痛了…青春期所特有的，无法掌控好与他人的距离而互相摩擦产生的，青涩又让人无法忘怀的痛楚", "ctime": "2023-08-12 03:06:40", "like": 262, "replies": [{"avatar": "/static/pic/i0.hdslb.com/bfs/face/3a6cc53a8fb291ef90080e72e80e37af05727f45.jpg", "uname": "冈山桃太郎", "current_level": 6, "vipStatus": 1, "is_senior_member": 0, "message": "充满了青春期这一自我究极成长时期的幻想寄托", "ctime": "2023-08-12 03:14:52", "like": 4}, {"avatar": "/static/pic/i1.hdslb.com/bfs/face/2fd1be1692458b9122c15f747d29872abee8eeeb.jpg", "uname": "徊眸_D名剑", "current_level": 5, "vipStatus": 0, "is_senior_member": 0, "message": "不单纯是青春期的问题，这里tmr明显是从小患有心理障碍，缺乏正常的社交能力，执着于某些大多数人无法理解的特殊事物。所以她才说“想要成为人”，在她的认知中自己和正常的人差很多。", "ctime": "2023-08-12 05:33:53", "like": 48}, {"avatar": "/static/pic/i2.hdslb.com/bfs/face/692071020f16bba563b048164873cb4f7333642e.jpg", "uname": "無敵小狗", "current_level": 5, "vipStatus": 0, "is_senior_member": 0, "message": "回復 @徊眸_D名剑 :应该不是心理障碍，感觉像是自闭症", "ctime": "2023-08-12 12:43:49", "like": 8}], "sub_reply_entry_text": "共4条回复", "pictures": []}, {"avatar": "/static/pic/i1.hdslb.com/bfs/face/6b8d30ee032b7356c9b5f5f1a059cfc8ba1fb439.jpg", "pendant": "/static/pic/i1.hdslb.com/bfs/garb/item/42d8c3e761097adac892b01bb070bdab8a60f52e.png", "uname": "白亚翔子", "current_level": 6, "vipStatus": 1, "is_senior_member": 0, "user_sailing": {"id": 37821, "name": "東雪蓮", "image": "/static/pic/i0.hdslb.com/bfs/garb/item/62081391a74be843e6be5860cb167769b1bb70ae.png", "jump_url": "https://www.bilibili.com/h5/mall/equity-link/home?navhide=1&item_id=37821&part=card_bg&f_source=garb&from=reply&vmid=37498399", "fan": {"is_fan": 1, "number": 3615, "color": "#b7a8cc", "name": "東雪蓮", "num_desc": "003615"}, "type": "suit"}, "message": "不得不再次感叹my go剧情文本编排上的高质量和高完成度，重新看一遍第三季真的能重新发现很多细节和台词上的伏笔，直接连接了过去和未来一堆的回旋镖，我宣布这里是回旋镖广场[doge]", "ctime": "2023-08-12 02:59:44", "like": 99, "replies": [{"avatar": "/static/pic/i0.hdslb.com/bfs/face/47c26f37c8f3b03ace1e20c73e27c043f49511fb.jpg", "uname": "阿洛娜铁咩", "current_level": 4, "vipStatus": 1, "is_senior_member": 0, "message": "设计得真的精妙，必须要反复看、回头看、配合弹幕一起看，每次都有新的体会[大哭]", "ctime": "2023-08-18 03:50:26", "like": 3}, {"avatar": "/static/pic/i1.hdslb.com/bfs/face/6b8d30ee032b7356c9b5f5f1a059cfc8ba1fb439.jpg", "uname": "白亚翔子", "current_level": 6, "vipStatus": 1, "is_senior_member": 0, "message": "回复 @阿洛娜铁咩 : 常看常新[tv_目瞪口呆]", "ctime": "2023-08-18 05:38:14", "like": 2}], "sub_reply_entry_text": "共2条回复", "pictures": []}, {"avatar": "/static/pic/i0.hdslb.com/bfs/face/9a1c71923ae2e862f59ab611e60979aa6f935950.jpg", "pendant": "", "uname": "ちはやあのん", "current_level": 5, "vipStatus": 1, "is_senior_member": 0, "user_sailing": "", "message": "mygo，e3，是我曾期待孤独摇滚成为的样子，年度单集提名，情绪流的佳肴。平和的主观视点下（切镜逻辑并未完全遵从人眼视点，很多地方的处理只是有意弱化了人物在场）灯的存在完全展露，收集的、蜷缩的、书写的姿态都是维系自我的手段（本集就展现了CRYCHIC变为她存在总和的过程），无论是肉身的与观众同化的凝视，还是用镜子囊括五人同在的瞬间（正视自己的时刻是很少的，而同在给予了灯自视的勇气），或者大胆而私心地唱着“永远”，灯内面的炽热如此直观。<br><br>属于她们的第一次live，立体的影像里只剩下歌曲，灯虔诚而忘我地在洁白的世界里吐出私人的字句。好像没法看清任何一个人，却又能明确感受到陪伴的影子。上pan至甜蜜幻觉似的光晕，而又下落到坚实而幸福的“我们”的时间。（这完美诠释了CRYCHIC即是［春日影］）<br><br>可是，这种幸福在下一刻就被击溃了，慌乱的注视与渐强的耳鸣，就像灯的藏品被偷走、敲碎了一般，［存在］出现了巨大的空洞。", "ctime": "2023-08-12 01:50:30", "like": 96, "replies": [], "sub_reply_entry_text": "", "pictures": []}, {"avatar": "/static/pic/i2.hdslb.com/bfs/face/46a02d4d97e31a64cd4a70449cede083b9cfdb7c.jpg", "pendant": "/static/pic/i2.hdslb.com/bfs/garb/item/0c8e7d627a35c378b757f39419889ef1fcc0ed9b.png", "uname": "南枫夹雪", "current_level": 6, "vipStatus": 1, "is_senior_member": 0, "user_sailing": "", "message": "第三集太神了，全程第一视角<br>回忆太梦幻太美好了，看完祥子都成我心里白月光了（x<br>旧团太美好破灭的又如此突然，坏了，我也成保皇派了", "ctime": "2023-08-12 01:49:04", "like": 99, "replies": [{"avatar": "/static/pic/i0.hdslb.com/bfs/face/d3cda2536c97ad75298c83eae72e36bbc31ede47.jpg", "uname": "Muimoi", "current_level": 5, "vipStatus": 0, "is_senior_member": 0, "message": "大场奈奈：我懂！重演的revue!", "ctime": "2023-08-13 20:35:54", "like": 10}], "sub_reply_entry_text": "共1条回复", "pictures": []}, {"avatar": "/static/pic/i1.hdslb.com/bfs/face/b189f15ff8f0eebdb4ff0d562db3dc088e27fd22.jpg", "pendant": "", "uname": "strongding", "current_level": 6, "vipStatus": 0, "is_senior_member": 1, "user_sailing": "", "message": "这集实在是太优秀了 每一秒都不浪费", "ctime": "2023-08-12 01:39:15", "like": 0, "replies": [], "sub_reply_entry_text": "", "pictures": []}, {"avatar": "/static/pic/i1.hdslb.com/bfs/face/5870916c521014bc1bd6a3e4e171c03c4150b576.jpg", "pendant": "", "uname": "ANON_TOKYO", "current_level": 6, "vipStatus": 1, "is_senior_member": 0, "user_sailing": {"id": 1681368254001, "name": "千禧辣妹酷洛米", "image": "/static/pic/i0.hdslb.com/bfs/baselabs/op/31fa91a960e1ec4ccf4427dd9120dee12b397d23f8a13c45f56f7457af9a6180.png", "jump_url": "https://www.bilibili.com/h5/mall/equity-link/home?navhide=1&item_id=1681368254001&part=card_bg&f_source=garb&from=reply&vmid=525580", "fan": {"is_fan": 1, "number": 256, "color": "#FF6FA9", "name": "千禧辣妹酷洛米", "num_desc": "000256"}, "type": "suit"}, "message": "灯从小就喜欢玩rock啊（察觉）", "ctime": "2023-08-12 01:23:23", "like": 1, "replies": [], "sub_reply_entry_text": "", "pictures": []}, {"avatar": "/static/pic/i1.hdslb.com/bfs/face/835a4801069d9c58a4d8e0b8f97d32a15c344834.jpg", "pendant": "", "uname": "EAYER", "current_level": 6, "vipStatus": 0, "is_senior_member": 0, "user_sailing": {"id": 2642, "name": "三周年恋曲", "image": "/static/pic/i0.hdslb.com/bfs/garb/item/40c3dda36cd5381ad4de0c284ac2470c6da6bc00.png", "jump_url": "https://www.bilibili.com/h5/mall/equity-link/home?navhide=1&item_id=2642&part=card_bg&f_source=garb&from=reply&vmid=10055770", "fan": {"is_fan": 1, "number": 71460, "color": "#e47ed3", "name": "会员购3周年", "num_desc": "071460"}, "type": "suit"}, "message": "呜呜呜，这集太棒了", "ctime": "2023-08-12 01:21:02", "like": 0, "replies": [], "sub_reply_entry_text": "", "pictures": []}, {"avatar": "/static/pic/i1.hdslb.com/bfs/face/384f53c95f45e1582bac7f380f55084c62a2e68e.jpg", "pendant": "", "uname": "兰登Yukino", "current_level": 5, "vipStatus": 0, "is_senior_member": 0, "user_sailing": "", "message": "灯：祥子，我的友人啊，为什么要离我而去…", "ctime": "2023-08-12 01:13:04", "like": 50, "replies": [{"avatar": "/static/pic/i1.hdslb.com/bfs/face/4767cfd1fe31490416201b12e0519971fec212e2.jpg", "uname": "Italo_Frantz_2nd", "current_level": 6, "vipStatus": 0, "is_senior_member": 0, "message": "我去别，少歌剧场版开场华恋那个心碎的声线…", "ctime": "2023-08-12 08:26:31", "like": 4}], "sub_reply_entry_text": "共1条回复", "pictures": []}, {"avatar": "/static/pic/i1.hdslb.com/bfs/face/a5518f8e853d80f0c5c79cf6e58453c997c919fb.jpg", "pendant": "/static/pic/i1.hdslb.com/bfs/garb/item/0c8e7d627a35c378b757f39419889ef1fcc0ed9b.png", "uname": "EquinoxGalaxy", "current_level": 6, "vipStatus": 1, "is_senior_member": 0, "user_sailing": {"id": 55651, "name": "明日方舟-愚夜密函", "image": "/static/pic/i0.hdslb.com/bfs/garb/item/a59af8ad49c1ea6a86d5975a98af081a29670a7e.png", "jump_url": "https://www.bilibili.com/h5/mall/equity-link/home?navhide=1&item_id=55651&part=card_bg&f_source=garb&from=reply&vmid=37630402", "fan": {"is_fan": 1, "number": 8421, "color": "#ec3d3d", "name": "明日方舟", "num_desc": "008421"}, "type": "suit"}, "message": "举目破败[明日方舟·音律联觉-愚夜密函_不好意思]", "ctime": "2023-08-12 01:09:24", "like": 0, "replies": [], "sub_reply_entry_text": "", "pictures": []}, {"avatar": "/static/pic/i1.hdslb.com/bfs/face/835a4801069d9c58a4d8e0b8f97d32a15c344834.jpg", "pendant": "", "uname": "EAYER", "current_level": 6, "vipStatus": 0, "is_senior_member": 0, "user_sailing": {"id": 2642, "name": "三周年恋曲", "image": "/static/pic/i0.hdslb.com/bfs/garb/item/40c3dda36cd5381ad4de0c284ac2470c6da6bc00.png", "jump_url": "https://www.bilibili.com/h5/mall/equity-link/home?navhide=1&item_id=2642&part=card_bg&f_source=garb&from=reply&vmid=10055770", "fan": {"is_fan": 1, "number": 71460, "color": "#e47ed3", "name": "会员购3周年", "num_desc": "071460"}, "type": "suit"}, "message": "好喜欢祥子[大哭]太温柔了。", "ctime": "2023-08-12 00:59:20", "like": 0, "replies": [], "sub_reply_entry_text": "", "pictures": []}, {"avatar": "/static/pic/i2.hdslb.com/bfs/face/cf75ab04215d976e116f107dea7cea44a78b7915.jpg", "pendant": "/static/pic/i2.hdslb.com/bfs/garb/item/8dda493572f895f8888cd2c66a78349162726c6b.png", "uname": "天际见归舟", "current_level": 6, "vipStatus": 0, "is_senior_member": 0, "user_sailing": {"id": 5355, "name": "乙女音", "image": "/static/pic/i0.hdslb.com/bfs/garb/item/c687abe581a969183dd4efc4415cea08475da09a.png", "jump_url": "https://www.bilibili.com/h5/mall/equity-link/home?navhide=1&item_id=5355&part=card_bg&f_source=garb&from=reply&vmid=32204831", "fan": {"is_fan": 1, "number": 996, "color": "#e495dc", "name": "乙女音", "num_desc": "000996"}, "type": "suit"}, "message": "再看一次第三集，真的是太美好了，难怪让人念念不忘，无法释怀，费尽心机也要重组", "ctime": "2023-08-12 00:57:42", "like": 3, "replies": [], "sub_reply_entry_text": "", "pictures": []}, {"avatar": "/static/pic/i1.hdslb.com/bfs/face/2b09b76aff19428e7d59a62a78a8e735bb71266f.jpg", "pendant": "/static/pic/i1.hdslb.com/bfs/garb/item/63db246f6a657190d79415af47fa0478013f9c05.png", "uname": "见习贤者末闻", "current_level": 6, "vipStatus": 1, "is_senior_member": 0, "user_sailing": {"id": 5296, "name": "提摩西小队", "image": "/static/pic/i0.hdslb.com/bfs/garb/item/9c76b1e337ecb2dd840eff4022f87314f8a8b5ca.png", "jump_url": "https://www.bilibili.com/h5/mall/equity-link/home?navhide=1&item_id=5296&part=card_bg&f_source=garb&from=reply&vmid=18201487", "fan": {"is_fan": 1, "number": 19102, "color": "#b78031", "name": "提摩西小队", "num_desc": "019102"}, "type": "suit"}, "message": "最白月光的一集[提摩西小队_我死了][提摩西小队_我死了][提摩西小队_我死了]", "ctime": "2023-08-12 00:50:49", "like": 9, "replies": [], "sub_reply_entry_text": "", "pictures": []}, {"avatar": "/static/pic/i1.hdslb.com/bfs/face/c325ac5190623438323206a8bb720bc7ec4f6132.jpg", "pendant": "", "uname": "阿尔伯特", "current_level": 6, "vipStatus": 1, "is_senior_member": 0, "user_sailing": "", "message": "谁遇到大祥能不迷糊的？硬撑罢了！谁遇到大祥能不迷糊的？硬撑罢了！谁遇到大祥能不迷糊的？硬撑罢了！谁遇到大祥能不迷糊的？硬撑罢了！谁遇到大祥能不迷糊的？硬撑罢了！谁遇到大祥能不迷糊的？硬撑罢了！谁遇到大祥能不迷糊的？硬撑罢了！谁遇到大祥能不迷糊的？硬撑罢了！谁遇到大祥能不迷糊的？硬撑罢了！谁遇到大祥能不迷糊的？硬撑罢了！", "ctime": "2023-08-12 00:49:52", "like": 14, "replies": [{"avatar": "/static/pic/i1.hdslb.com/bfs/face/2fd1be1692458b9122c15f747d29872abee8eeeb.jpg", "uname": "徊眸_D名剑", "current_level": 5, "vipStatus": 0, "is_senior_member": 0, "message": "md，忍不了，一拳把CRYCHIC打爆！", "ctime": "2023-08-12 05:34:48", "like": 1}, {"avatar": "/static/pic/i2.hdslb.com/bfs/face/64f511dcf220bf2fe07b776cec40b706f4627d9a.jpg", "uname": "NagasakiSoyo", "current_level": 4, "vipStatus": 0, "is_senior_member": 0, "message": "回复 @徊眸_D名剑 :md，忍不了，创建新团mygo!", "ctime": "2023-08-13 13:58:40", "like": 0}], "sub_reply_entry_text": "共2条回复", "pictures": []}, {"avatar": "/static/pic/i0.hdslb.com/bfs/face/e0138eecdc2c9b95c7a54542c39cab3160ca30d8.jpg", "pendant": "/static/pic/i0.hdslb.com/bfs/garb/item/4f8f3f1f2d47f0dad84f66aa57acd4409ea46361.png", "uname": "弦巻Kokoro", "current_level": 5, "vipStatus": 0, "is_senior_member": 0, "user_sailing": {"id": 54154, "name": "代号洛天依", "image": "/static/pic/i0.hdslb.com/bfs/garb/item/524e1a2be570327338ac3f870cbdac4bf736bf3e.png", "jump_url": "https://www.bilibili.com/h5/mall/equity-link/home?navhide=1&item_id=54154&part=card_bg&f_source=garb&from=reply&vmid=438118017", "fan": {"is_fan": 1, "number": 7313, "color": "#32c1dc", "name": "代号洛天依", "num_desc": "007313"}, "type": "suit"}, "message": "好好好[打call]", "ctime": "2023-08-12 00:48:22", "like": 1, "replies": [], "sub_reply_entry_text": "", "pictures": []}, {"avatar": "/static/pic/i1.hdslb.com/bfs/face/4efa37e353adb4e9636dc73ff5ee6cbcf3909f2b.jpg", "pendant": "", "uname": "枣团", "current_level": 6, "vipStatus": 1, "is_senior_member": 0, "user_sailing": "", "message": "最喜欢的一集，不管是叙事性还是艺术观赏都是很强的一集", "ctime": "2023-08-12 00:45:45", "like": 6, "replies": [], "sub_reply_entry_text": "", "pictures": []}, {"avatar": "/static/pic/i1.hdslb.com/bfs/face/94aa8b10f9f729cd69c0b5178c72b723f35b0962.jpg", "pendant": "", "uname": "S-O-U-L", "current_level": 6, "vipStatus": 1, "is_senior_member": 0, "user_sailing": "", "message": "真的很喜欢第三集，最佳单集[打call]", "ctime": "2023-08-12 00:31:33", "like": 3, "replies": [], "sub_reply_entry_text": "", "pictures": []}, {"avatar": "/static/pic/i2.hdslb.com/bfs/face/bfa576253bc7eb1ad05daa1591e0322a447c1834.jpg", "pendant": "/static/pic/i2.hdslb.com/bfs/garb/item/117d81597454ca63495a8a6cfc986611795bba18.png", "uname": "我叶莲娜盛世美颜", "current_level": 6, "vipStatus": 1, "is_senior_member": 0, "user_sailing": {"id": 55651, "name": "明日方舟-愚夜密函", "image": "/static/pic/i0.hdslb.com/bfs/garb/item/a59af8ad49c1ea6a86d5975a98af081a29670a7e.png", "jump_url": "https://www.bilibili.com/h5/mall/equity-link/home?navhide=1&item_id=55651&part=card_bg&f_source=garb&from=reply&vmid=11885108", "fan": {"is_fan": 1, "number": 9331, "color": "#ec3d3d", "name": "明日方舟", "num_desc": "009331"}, "type": "suit"}, "message": "灯∶痛！太痛了！祥子，你为何要躲着我呢？", "ctime": "2023-08-12 00:21:43", "like": 5, "replies": [], "sub_reply_entry_text": "", "pictures": []}, {"avatar": "/static/pic/i2.hdslb.com/bfs/face/c5b0aa1d6c34e27a5a45bdd2f153ca2856a02178.jpg", "pendant": "/static/pic/i2.hdslb.com/bfs/garb/item/4f8f3f1f2d47f0dad84f66aa57acd4409ea46361.png", "uname": "Yuiii_Hao", "current_level": 5, "vipStatus": 1, "is_senior_member": 0, "user_sailing": {"id": 46582, "name": "2233兔年新春", "image": "/static/pic/i0.hdslb.com/bfs/garb/item/c2190807de495730d37b7f9d5fe65dc1abb163de.png", "jump_url": "https://www.bilibili.com/h5/mall/equity-link/home?navhide=1&item_id=46582&part=card_bg&f_source=garb&from=reply&vmid=470511893", "fan": {"is_fan": 1, "number": 3002, "color": "#d23f52", "name": "2233兔年新春", "num_desc": "003002"}, "type": "suit"}, "message": "好耶", "ctime": "2023-08-12 00:15:28", "like": 1, "replies": [], "sub_reply_entry_text": "", "pictures": []}, {"avatar": "/static/pic/i2.hdslb.com/bfs/face/e004c3c7d0ce60f50dcf03b9ba8ae2db2aa5a29f.jpg", "pendant": "/static/pic/i2.hdslb.com/bfs/garb/item/0cc9d8cfa62d589c9caac1da2e52f0365514941a.png", "uname": "超级无敌可爱的X毛", "current_level": 6, "vipStatus": 1, "is_senior_member": 0, "user_sailing": {"id": 1677606299001, "name": "草莓猫Taffy", "image": "/static/pic/i0.hdslb.com/bfs/baselabs/op/cafb0e6aec4ed1604f5a5751ce34728e9688fb762c4133a52cbd0db8d4fac6aa.png", "jump_url": "https://www.bilibili.com/h5/mall/equity-link/home?navhide=1&item_id=1677606299001&part=card_bg&f_source=garb&from=reply&vmid=37616876", "fan": {"is_fan": 1, "number": 14, "color": "#F2466F", "name": "草莓猫Taffy", "num_desc": "000014"}, "type": "suit"}, "message": "第三集复活赛终究还是打赢了叔叔", "ctime": "2023-08-12 00:13:19", "like": 26, "replies": [], "sub_reply_entry_text": "", "pictures": []}], "top_replies": []}