{"errno": 0, "totalPage": 32, "replies": [{"avatar": "https://i1.hdslb.com/bfs/face/7051f10c701279e3f40e07d4875d55fd5634dd0c.jpg", "uname": "永远的Mzero", "current_level": 5, "vipStatus": 0, "is_senior_member": 0, "message": "回复 @只有名名名 :开始我以为这张图是发生在第十集的时间线，现在我还要回去考证一下[捂脸]", "ctime": "2023-08-11 19:57:55", "like": 6}, {"avatar": "https://i1.hdslb.com/bfs/face/9f1ecc89663fa49496f4d484c0564f0c2cdad39f.jpg", "uname": "燥侯大学毕业", "current_level": 6, "vipStatus": 0, "is_senior_member": 0, "message": "我去", "ctime": "2023-08-11 20:04:38", "like": 0}, {"avatar": "https://i1.hdslb.com/bfs/face/492e06937bb3ad2cfe8cc8615d7f2f8d514be044.jpg", "uname": "纯真丁一狼", "current_level": 6, "vipStatus": 0, "is_senior_member": 0, "message": "BV1zm4y1p727", "ctime": "2023-08-11 20:04:48", "like": 3}, {"avatar": "https://i0.hdslb.com/bfs/face/75a8152eedd7ad4bc8f2ec3210396a87736409be.jpg", "uname": "草石虫", "current_level": 6, "vipStatus": 1, "is_senior_member": 0, "message": "边上是睦头人？", "ctime": "2023-08-11 20:19:47", "like": 3}, {"avatar": "https://i2.hdslb.com/bfs/face/987d6c0a74dd9a6e82c85383ea5664f25b174101.jpg", "uname": "wood0083", "current_level": 5, "vipStatus": 1, "is_senior_member": 0, "message": "离谱！[惊讶]", "ctime": "2023-08-11 20:59:41", "like": 2}, {"avatar": "http://i1.hdslb.com/bfs/face/a31a7d1a82d2d1ef3602788c1dbe063b428de286.jpg", "uname": "吕田丨口电", "current_level": 6, "vipStatus": 1, "is_senior_member": 0, "message": "初中校服裙子不一样的，应该只是有点像的巧合", "ctime": "2023-08-11 21:00:41", "like": 3}, {"avatar": "https://i0.hdslb.com/bfs/face/e99ca06e5c746978587c8ccb8db34613485d1720.jpg", "uname": "TheRainbowO_A", "current_level": 6, "vipStatus": 1, "is_senior_member": 1, "message": "确实 理论上来讲 原三年生毕业之后的时间线上她俩确实该入校了=。=", "ctime": "2023-08-11 21:20:29", "like": 0}, {"avatar": "https://i0.hdslb.com/bfs/face/df816c428c981d85703e5bb4cbbae75219237db4.jpg", "uname": "玖枵闲人", "current_level": 6, "vipStatus": 1, "is_senior_member": 1, "message": "回复 @吕田丨口电 :也可能是当时设定好了人物没设定好时间线吧，我记得mygo一开始设定为大学？", "ctime": "2023-08-11 21:49:42", "like": 3}, {"avatar": "https://i2.hdslb.com/bfs/face/5f59056fa2a0a1894ffa4eb345ad030fddd15525.jpg", "uname": "兰酱今天吃摩卡", "current_level": 5, "vipStatus": 0, "is_senior_member": 0, "message": "不对啊，她俩不是比monica低一届吗", "ctime": "2023-08-11 22:13:06", "like": 2}, {"avatar": "https://i2.hdslb.com/bfs/face/1f260acbad0ad605f3326cff11dd49ec93284175.jpg", "uname": "teio动啊", "current_level": 5, "vipStatus": 0, "is_senior_member": 0, "message": "巧合吧，白毛发型不一样", "ctime": "2023-08-11 22:28:37", "like": 6}]}