{"errno": 0, "totalPage": 2, "replies": [{"avatar": "https://i1.hdslb.com/bfs/face/ef568d55f8ba3f766d2a2fdc86ffa301639c0de1.jpg", "uname": "羔籍姬泄攻橙湿", "current_level": 5, "vipStatus": 1, "is_senior_member": 0, "message": "那你刚好卡在高潮的那个点前", "ctime": "2023-10-01 23:11:06", "like": 0}, {"avatar": "https://i1.hdslb.com/bfs/face/d69757366068ac52aeeac964dd7c9d479743a1b6.jpg", "uname": "叫我密宝就好", "current_level": 6, "vipStatus": 0, "is_senior_member": 1, "message": "因为10.1截止，后面不知道还会不会返场", "ctime": "2023-10-01 23:15:15", "like": 1}]}