{"errno": 0, "totalPage": 249, "all_count": 15263, "replies": [{"rpid": 217056398688, "avatar": "http://i0.hdslb.com/bfs/face/262c15ec0db67ef04a4563464d64261465f228dc.jpg", "pendant": "", "uname": "摸向未来", "current_level": 6, "vipStatus": 0, "is_senior_member": 0, "fans_detail": "", "user_sailing": "", "message": "mujica 给我一种SH的感觉  但伪物虚幻感太严重，只是单纯的强度，无法引起共鸣     个人更喜欢MY GO", "ctime": "2024-04-15 23:32:21", "like": 5, "pictures": [], "replies": [], "sub_reply_entry_text": "", "rcount": 0}, {"rpid": 215964170432, "avatar": "https://i1.hdslb.com/bfs/face/9f4f7b4f210f42cdf9140d4d54ae9b61cdeaae7f.jpg", "pendant": "", "uname": "_阿芒特之森", "current_level": 5, "vipStatus": 0, "is_senior_member": 0, "fans_detail": "", "user_sailing": "", "message": "请教一下，这是如何做到视频并没有删除，这是隐藏起来又释放了，我记得b站没有隐藏视频的功能呀，看这个视频之前说不是去年夏天之时。", "ctime": "2024-04-08 16:27:16", "like": 5, "pictures": [], "replies": [{"avatar": "https://i0.hdslb.com/bfs/face/29f1a91f0fee19824c060b4535951c8aa1b8e968.jpg", "uname": "羟基卤蛋烃", "current_level": 6, "vipStatus": 1, "is_senior_member": 0, "message": "可以隐藏的，只不过普通用户没这个权限", "ctime": "2024-04-08 16:59:17", "like": 7}, {"avatar": "https://i1.hdslb.com/bfs/face/9f4f7b4f210f42cdf9140d4d54ae9b61cdeaae7f.jpg", "uname": "_阿芒特之森", "current_level": 5, "vipStatus": 0, "is_senior_member": 0, "message": "回复 @羟基卤蛋烃 :@羟基卤蛋烃  好吧。这真的是稀缺的一项权限呢。", "ctime": "2024-04-08 17:07:11", "like": 0}, {"avatar": "https://i2.hdslb.com/bfs/face/9247965fc8528dfaf7a31b0a32a1fa5b5537fbf7.jpg", "uname": "轻--心", "current_level": 6, "vipStatus": 0, "is_senior_member": 0, "message": "嘶，不过播放数也在", "ctime": "2024-04-08 16:31:00", "like": 0}], "sub_reply_entry_text": "共6条回复", "rcount": 6}, {"rpid": 216171729728, "avatar": "http://i1.hdslb.com/bfs/face/fa1a47768e29af465e0c6b909d67cd42e459dfed.jpg", "pendant": "", "uname": "小米粥与咸鸭蛋", "current_level": 6, "vipStatus": 1, "is_senior_member": 0, "fans_detail": "", "user_sailing": {"id": 34846, "name": "星瞳", "image": "https://i0.hdslb.com/bfs/garb/item/a3ae7e6e31113d8c2a4d72157980df81f3735773.png", "jump_url": "https://www.bilibili.com/h5/mall/equity-link/collect-home?item_id=34846&isdiy=0&part=card_bg&from=reply&f_source=garb&vmid=13704571&native.theme=1&navhide=1", "fan": {"is_fan": 1, "number": 31150, "color": "#df6a74", "name": "星瞳", "num_desc": "031150", "num_prefix": "NO.", "color_format": {"start_point": "0,0", "end_point": "0,100", "colors": ["#df6a74FF", "#df6a74FF"], "gradients": [0, 100]}}, "type": "suit"}, "message": "客服小祥也许想对灯说的话<br>我从不后悔与灯组建crychic，因为你的歌词就是内心的呐喊。那晚的春日影太美了，可我已经不能再回应它的呼唤。Crychic太好了，可我已不能回到过去。如果说当初的我有幸完成了对灯的救赎，请你务必要完成对mygo的救赎。现在，请原谅我该死的自尊，只能将千言万语化作一句——祝你幸福。", "ctime": "2024-04-10 01:26:42", "like": 5, "pictures": [], "replies": [], "sub_reply_entry_text": "", "rcount": 0}, {"rpid": 216283081440, "avatar": "https://i2.hdslb.com/bfs/face/454d5129a76724414075e0f84ef4ad5b7dfefe10.jpg", "pendant": "https://i2.hdslb.com/bfs/garb/item/a0c0e3d5988c1ef878f3ef51ec9f6d9e5826d6dd.png", "uname": "网友高松燈", "current_level": 6, "vipStatus": 1, "is_senior_member": 1, "fans_detail": "", "user_sailing": {"id": 32859, "name": "奥特曼系列", "image": "https://i0.hdslb.com/bfs/garb/item/a4120c9656c2044eb32427bba89fb0ec2c1aa5f1.png", "jump_url": "https://www.bilibili.com/h5/mall/equity-link/collect-home?item_id=32859&isdiy=0&part=card_bg&from=reply&f_source=garb&vmid=397671284&native.theme=1&navhide=1", "fan": {"is_fan": 1, "number": 2020, "color": "#FF6633", "name": "奥特曼系列", "num_desc": "002020", "num_prefix": "NO.", "color_format": {"start_point": "0,0", "end_point": "0,100", "colors": ["#FF6633FF", "#FF6633FF"], "gradients": [0, 100]}}, "type": "suit"}, "message": "来自麻浦高中的两位少女高赫奎和李祥赫，此时站在了命运的舞台中央，bang dream冠军奖杯此刻就在她们眼前…<br>一年后<br>李祥赫回想起一年前高赫奎击败自己的事情，放下了个人荣辱的心结，坦言到：这第四个冠军，我只想献给我的的队友", "ctime": "2024-04-10 21:46:58", "like": 5, "pictures": [], "replies": [{"avatar": "https://i0.hdslb.com/bfs/face/470c1a7817b7d4ea8b7783b16db8fa2ac2ab00d2.jpg", "uname": "身背步枪娜塔莎", "current_level": 6, "vipStatus": 1, "is_senior_member": 0, "message": "祥天帝活出第二世了", "ctime": "2024-04-10 23:54:29", "like": 0}], "sub_reply_entry_text": "共1条回复", "rcount": 1}, {"rpid": 216609162528, "avatar": "https://i0.hdslb.com/bfs/face/2a1420f84aae10c6b0f51a1861a39df803b4c85c.jpg", "pendant": "https://i0.hdslb.com/bfs/garb/item/4ad130e4068f88c54728ac510a172b97e187826f.png", "uname": "Nomorelxn", "current_level": 6, "vipStatus": 0, "is_senior_member": 0, "fans_detail": "", "user_sailing": {"id": 33494, "name": "乃琳Queen", "image": "https://i0.hdslb.com/bfs/garb/item/34f8c1ef43332883f62e17fed44c1a70930e4811.png", "jump_url": "https://www.bilibili.com/h5/mall/equity-link/collect-home?item_id=33494&isdiy=0&part=card_bg&from=reply&f_source=garb&vmid=29558028&native.theme=1&navhide=1", "fan": {"is_fan": 1, "number": 44523, "color": "#576690", "name": "乃琳Queen", "num_desc": "044523", "num_prefix": "NO.", "color_format": {"start_point": "0,0", "end_point": "0,100", "colors": ["#576690FF", "#576690FF"], "gradients": [0, 100]}}, "type": "suit"}, "message": "你知道的，祥子是我的兄弟，初华强的不可思议，后面忘了，至于mygo，祝她们一切顺利", "ctime": "2024-04-13 02:11:32", "like": 5, "pictures": [], "replies": [], "sub_reply_entry_text": "", "rcount": 0}, {"rpid": 216291662752, "avatar": "https://i0.hdslb.com/bfs/face/b9e78c5874c0adc8361082245e46d5dc5014b8a7.jpg", "pendant": "https://i0.hdslb.com/bfs/garb/item/e7e38de135edbd9f248067944663824bdba622b6.png", "uname": "鸥洲人宣布接管此区域", "current_level": 6, "vipStatus": 1, "is_senior_member": 0, "fans_detail": "", "user_sailing": {"id": 67807, "name": "BanGDream！", "image": "https://i0.hdslb.com/bfs/garb/item/bbc13f949040bce6a154d01f9179e8580642455e.png", "jump_url": "https://www.bilibili.com/h5/mall/equity-link/collect-home?item_id=67807&isdiy=0&part=card_bg&from=reply&f_source=garb&vmid=37254381&native.theme=1&navhide=1", "fan": {"is_fan": 1, "number": 11423, "color": "#F67E95", "name": "BanGDream", "num_desc": "011423", "num_prefix": "NO.", "color_format": {"start_point": "0,0", "end_point": "0,100", "colors": ["#F67E95FF", "#F67E95FF"], "gradients": [0, 100]}}, "type": "suit"}, "message": "话说喵梦是不是邦邦头一回弄出社会人人设，之前我记得全是学生", "ctime": "2024-04-10 22:41:35", "like": 5, "pictures": [], "replies": [{"avatar": "http://i2.hdslb.com/bfs/face/cdf35f8184b371f2ff9ab2dc4648088c540510ab.jpg", "uname": "乖乖的小小君", "current_level": 6, "vipStatus": 1, "is_senior_member": 0, "message": "她不一定是社会人士，别被现在的迷雾骗了", "ctime": "2024-04-10 22:49:47", "like": 6}, {"avatar": "https://i2.hdslb.com/bfs/face/0b3bf50ff96d6e61d22d612a0292d7f02caa3190.jpg", "uname": "比宇宙还近的地方", "current_level": 6, "vipStatus": 0, "is_senior_member": 0, "message": "隔壁夏美不也是边上学边拍视频么", "ctime": "2024-04-10 23:00:16", "like": 6}], "sub_reply_entry_text": "共5条回复", "rcount": 5}, {"rpid": 185922099744, "avatar": "https://i2.hdslb.com/bfs/face/e4b6a67e5ff4ecdc5eab29b663774c600459bf3f.jpg", "pendant": "", "uname": "narutoandsasuke", "current_level": 6, "vipStatus": 0, "is_senior_member": 1, "fans_detail": "", "user_sailing": "", "message": "立希女士这是什么苦主模板[笑哭]", "ctime": "2023-09-14 21:41:27", "like": 6, "pictures": [], "replies": [], "sub_reply_entry_text": "", "rcount": 0}, {"rpid": 216166865216, "avatar": "https://i2.hdslb.com/bfs/face/bfe086208f4a47bad65846f8a628853bef3952ac.jpg", "pendant": "", "uname": "吾非玉", "current_level": 6, "vipStatus": 1, "is_senior_member": 0, "fans_detail": "", "user_sailing": {"id": 1709791289001, "name": "这碗鱼的评论背景", "image": "https://i0.hdslb.com/bfs/baselabs/op/cd7b4a0251bd86db61bbaef9aff892bfc3011e8b9c4b8d64a59b11b72a6bd429.png", "jump_url": "https://www.bilibili.com/h5/mall/equity-link/collect-home?item_id=1709791289001&isdiy=0&part=card_bg&from=reply&f_source=garb&vmid=27215726&native.theme=1&navhide=1", "fan": {"is_fan": 0, "number": 0, "color": "", "name": "", "num_desc": "", "num_prefix": "", "color_format": null}, "type": "suit"}, "message": "满足，看的第四遍了", "ctime": "2024-04-10 00:32:09", "like": 5, "pictures": [], "replies": [], "sub_reply_entry_text": "", "rcount": 0}, {"rpid": 185921502112, "avatar": "https://i2.hdslb.com/bfs/face/b45cd90d0b5355153e4a78ab73df76a71c9d9210.jpg", "pendant": "https://i2.hdslb.com/bfs/garb/item/1bd44cef17dd365198e5021cb67aa9e8efe2e1c6.png", "uname": "星乃一歌゜", "current_level": 6, "vipStatus": 1, "is_senior_member": 1, "fans_detail": {"uid": 32316899, "medal_id": 728971, "medal_name": "迷子A", "score": 0, "level": 9, "intimacy": 0, "master_status": 0, "is_receive": 0, "medal_color": 866040552, "medal_color_end": 866040552, "medal_color_border": 782877673, "medal_color_name": 4283924408, "medal_color_level": 4288327890, "guard_level": 0, "guard_icon": "", "honor_icon": "", "medal_level_bg_color": 16777215}, "user_sailing": {"id": 67807, "name": "BanGDream！", "image": "https://i0.hdslb.com/bfs/garb/item/bbc13f949040bce6a154d01f9179e8580642455e.png", "jump_url": "https://www.bilibili.com/h5/mall/equity-link/collect-home?item_id=67807&isdiy=0&part=card_bg&from=reply&f_source=garb&vmid=32316899&native.theme=1&navhide=1", "fan": {"is_fan": 1, "number": 6935, "color": "#F67E95", "name": "BanGDream", "num_desc": "006935", "num_prefix": "NO.", "color_format": {"start_point": "0,0", "end_point": "0,100", "colors": ["#F67E95FF", "#F67E95FF"], "gradients": [0, 100]}}, "type": "suit"}, "message": "再见了，我最爱的mygo，入宅接近十年了这是第一部让我这么喜欢的新番，小羊，请带着我们的憧憬继续走下去吧，", "ctime": "2023-09-14 21:37:45", "like": 6, "pictures": [], "replies": [], "sub_reply_entry_text": "", "rcount": 0}, {"rpid": 216030552720, "avatar": "https://i1.hdslb.com/bfs/face/056195d592010febbf181ae772244bd1cd5edcfa.jpg", "pendant": "https://i1.hdslb.com/bfs/face/f2d3a85b611eb2ef13cb64415187e3e9fd487ec8.png", "uname": "醉酒乱来", "current_level": 6, "vipStatus": 1, "is_senior_member": 1, "fans_detail": "", "user_sailing": "", "message": "我去返场！", "ctime": "2024-04-09 00:35:20", "like": 5, "pictures": [], "replies": [], "sub_reply_entry_text": "", "rcount": 0}, {"rpid": 216775356000, "avatar": "http://i0.hdslb.com/bfs/face/6af21fd21e34fe12b72aca405bd4dc9b74a88faf.jpg", "pendant": "", "uname": "阿良良木历LY", "current_level": 5, "vipStatus": 1, "is_senior_member": 0, "fans_detail": "", "user_sailing": "", "message": "李世林:我，无畏契约", "ctime": "2024-04-14 05:19:37", "like": 5, "pictures": [], "replies": [], "sub_reply_entry_text": "", "rcount": 0}, {"rpid": 216005704000, "avatar": "https://i2.hdslb.com/bfs/face/764242cc9e7c020902a1f18d3bf997287164d28a.jpg", "pendant": "", "uname": "Nymphの苹果糖", "current_level": 6, "vipStatus": 0, "is_senior_member": 1, "fans_detail": "", "user_sailing": {"id": 50103, "name": "灰原哀", "image": "https://i0.hdslb.com/bfs/garb/item/d445f3dff120038422ab6186200c6a7c21444e45.png", "jump_url": "https://www.bilibili.com/h5/mall/equity-link/collect-home?item_id=50103&isdiy=0&part=card_bg&from=reply&f_source=garb&vmid=302978&native.theme=1&navhide=1", "fan": {"is_fan": 1, "number": 4097, "color": "#8463bc", "name": "灰原哀", "num_desc": "004097", "num_prefix": "NO.", "color_format": {"start_point": "0,0", "end_point": "0,100", "colors": ["#8463bcFF", "#8463bcFF"], "gradients": [0, 100]}}, "type": "suit"}, "message": "又看完一遍ave mujica，爽[打call]", "ctime": "2024-04-08 21:39:26", "like": 5, "pictures": [], "replies": [], "sub_reply_entry_text": "", "rcount": 0}, {"rpid": 215956751680, "avatar": "https://i2.hdslb.com/bfs/face/5d2c92beb774a4bb30762538bb102d23670ae9c0.gif", "pendant": "", "uname": "菅叶和", "current_level": 6, "vipStatus": 1, "is_senior_member": 0, "fans_detail": {"uid": 395900, "medal_id": 728971, "medal_name": "迷子A", "score": 0, "level": 22, "intimacy": 0, "master_status": 0, "is_receive": 0, "medal_color": 866040552, "medal_color_end": 866040552, "medal_color_border": 782877673, "medal_color_name": 4283924408, "medal_color_level": 4288327890, "guard_level": 0, "guard_icon": "", "honor_icon": "", "medal_level_bg_color": 16777215}, "user_sailing": {"id": 67807, "name": "BanGDream！", "image": "https://i0.hdslb.com/bfs/garb/item/bbc13f949040bce6a154d01f9179e8580642455e.png", "jump_url": "https://www.bilibili.com/h5/mall/equity-link/collect-home?item_id=67807&isdiy=0&part=card_bg&from=reply&f_source=garb&vmid=395900&native.theme=1&navhide=1", "fan": {"is_fan": 1, "number": 2194, "color": "#F67E95", "name": "BanGDream", "num_desc": "002194", "num_prefix": "NO.", "color_format": {"start_point": "0,0", "end_point": "0,100", "colors": ["#F67E95FF", "#F67E95FF"], "gradients": [0, 100]}}, "type": "suit"}, "message": "即将达到一百万匹力量", "ctime": "2024-04-08 15:15:37", "like": 5, "pictures": [], "replies": [], "sub_reply_entry_text": "", "rcount": 0}, {"rpid": 215943633840, "avatar": "https://i2.hdslb.com/bfs/face/0b11a504d63c149dbabee859e6c17a78401f423a.jpg", "pendant": "", "uname": "NoreBran", "current_level": 6, "vipStatus": 0, "is_senior_member": 1, "fans_detail": {"uid": 34573316, "medal_id": 728971, "medal_name": "迷子A", "score": 0, "level": 3, "intimacy": 0, "master_status": 0, "is_receive": 0, "medal_color": 866040552, "medal_color_end": 866040552, "medal_color_border": 782877673, "medal_color_name": 4283924408, "medal_color_level": 4288327890, "guard_level": 0, "guard_icon": "", "honor_icon": "", "medal_level_bg_color": 16777215}, "user_sailing": {"id": 1682250362001, "name": "摇光", "image": "https://i0.hdslb.com/bfs/baselabs/op/31d9b80248242cc8c48252ac617e608e0565efd27a915743572a41b3859be7f1.png", "jump_url": "https://www.bilibili.com/h5/mall/equity-link/collect-home?item_id=1682250362001&isdiy=0&part=card_bg&from=reply&f_source=garb&vmid=34573316&native.theme=1&navhide=1", "fan": {"is_fan": 1, "number": 5114, "color": "#1F98FF", "name": "治愈插画家丁丁框系列-摇光", "num_desc": "005114", "num_prefix": "NO.", "color_format": {"start_point": "0,0", "end_point": "0,100", "colors": ["#1F98FFFF", "#1F98FFFF"], "gradients": [0, 100]}}, "type": "suit"}, "message": "Sound Horizon 7th(x", "ctime": "2024-04-08 13:08:15", "like": 5, "pictures": [], "replies": [], "sub_reply_entry_text": "", "rcount": 0}, {"rpid": 215961631280, "avatar": "http://i2.hdslb.com/bfs/face/e43fd8b7955a6c6b793ccdeb48c7643b3212488c.jpg", "pendant": "", "uname": "你-改-悔-罢", "current_level": 5, "vipStatus": 0, "is_senior_member": 0, "fans_detail": "", "user_sailing": "", "message": "复权之时！", "ctime": "2024-04-08 16:03:18", "like": 5, "pictures": [], "replies": [], "sub_reply_entry_text": "", "rcount": 0}, {"rpid": 217028423808, "avatar": "https://i0.hdslb.com/bfs/face/d08dbfe5fefa21a8697099af5834fdf22788a65e.jpg", "pendant": "https://i0.hdslb.com/bfs/garb/item/42e3d2487f4ce3518bf5e721bc57becf6047e94f.png", "uname": "Justaste", "current_level": 6, "vipStatus": 0, "is_senior_member": 1, "fans_detail": "", "user_sailing": {"id": 3204, "name": "Kizuna AI", "image": "https://i0.hdslb.com/bfs/garb/item/d0bd3a90005e67787e6e243bea80b4c4bac63284.png", "jump_url": "https://www.bilibili.com/h5/mall/equity-link/collect-home?item_id=3204&isdiy=0&part=card_bg&from=reply&f_source=garb&vmid=195096033&native.theme=1&navhide=1", "fan": {"is_fan": 1, "number": 25639, "color": "#ff7fa0", "name": "Kizuna AI", "num_desc": "025639", "num_prefix": "NO.", "color_format": {"start_point": "0,0", "end_point": "0,100", "colors": ["#ff7fa0FF", "#ff7fa0FF"], "gradients": [0, 100]}}, "type": "suit"}, "message": "都说了要mygo一辈子了，在座的各位要好好保重身体到那一天才行呢[BanGDream_灯-放松][BanGDream_爱音-不解][BanGDream_乐奈-困][BanGDream_爽世-微笑][BanGDream_立希-怒]", "ctime": "2024-04-15 20:30:58", "like": 5, "pictures": [], "replies": [], "sub_reply_entry_text": "", "rcount": 0}, {"rpid": 216867839520, "avatar": "https://i2.hdslb.com/bfs/face/ea8b953e4d7e8e0e5180c94665cb96aad943609d.jpg", "pendant": "https://i2.hdslb.com/bfs/garb/item/4f8f3f1f2d47f0dad84f66aa57acd4409ea46361.png", "uname": "jenaimepas139", "current_level": 6, "vipStatus": 1, "is_senior_member": 1, "fans_detail": {"uid": 176530508, "medal_id": 728971, "medal_name": "迷子A", "score": 0, "level": 6, "intimacy": 0, "master_status": 0, "is_receive": 0, "medal_color": 866040552, "medal_color_end": 866040552, "medal_color_border": 782877673, "medal_color_name": 4283924408, "medal_color_level": 4288327890, "guard_level": 0, "guard_icon": "", "honor_icon": "", "medal_level_bg_color": 16777215}, "user_sailing": {"id": 2528, "name": "初音未来13周年", "image": "https://i0.hdslb.com/bfs/garb/item/7dbd22f700e0a7fe0c0d0da7b1a54241626bf1cd.png", "jump_url": "https://www.bilibili.com/h5/mall/equity-link/collect-home?item_id=2528&isdiy=0&part=card_bg&from=reply&f_source=garb&vmid=176530508&native.theme=1&navhide=1", "fan": {"is_fan": 1, "number": 41823, "color": "#07b6d5", "name": "初音未来周年纪念", "num_desc": "041823", "num_prefix": "NO.", "color_format": {"start_point": "0,0", "end_point": "0,100", "colors": ["#07b6d5FF", "#07b6d5FF"], "gradients": [0, 100]}}, "type": "suit"}, "message": "[BanGDream_爱音-不解][BanGDream_爽世-微笑][BanGDream_灯-放松][BanGDream_立希-怒][BanGDream_乐奈-困]", "ctime": "2024-04-14 18:50:10", "like": 8, "pictures": [], "replies": [], "sub_reply_entry_text": "", "rcount": 0}, {"rpid": 216221967488, "avatar": "https://i1.hdslb.com/bfs/face/55ead93b7ac463930932b9d19b2ddc70ed99b967.png", "pendant": "https://i1.hdslb.com/bfs/face/a959c72407b2ac553d4328fd76d55d0134e20f65.png", "uname": "暗夜的夜刃", "current_level": 6, "vipStatus": 1, "is_senior_member": 1, "fans_detail": {"uid": 5424874, "medal_id": 728971, "medal_name": "迷子A", "score": 0, "level": 21, "intimacy": 0, "master_status": 0, "is_receive": 0, "medal_color": 866040552, "medal_color_end": 866040552, "medal_color_border": 782877673, "medal_color_name": 4283924408, "medal_color_level": 4288327890, "guard_level": 0, "guard_icon": "", "honor_icon": "", "medal_level_bg_color": 16777215}, "user_sailing": {"id": 67807, "name": "BanGDream！", "image": "https://i0.hdslb.com/bfs/garb/item/bbc13f949040bce6a154d01f9179e8580642455e.png", "jump_url": "https://www.bilibili.com/h5/mall/equity-link/collect-home?item_id=67807&isdiy=0&part=card_bg&from=reply&f_source=garb&vmid=5424874&native.theme=1&navhide=1", "fan": {"is_fan": 1, "number": 7538, "color": "#F67E95", "name": "BanGDream", "num_desc": "007538", "num_prefix": "NO.", "color_format": {"start_point": "0,0", "end_point": "0,100", "colors": ["#F67E95FF", "#F67E95FF"], "gradients": [0, 100]}}, "type": "suit"}, "message": "[BanGDream_乐奈-困][BanGDream_立希-怒][BanGDream_灯-放松][BanGDream_爱音-不解][BanGDream_爽世-微笑]", "ctime": "2024-04-10 13:38:55", "like": 8, "pictures": [], "replies": [], "sub_reply_entry_text": "", "rcount": 0}, {"rpid": 185945331792, "avatar": "https://i1.hdslb.com/bfs/face/5ab9461eb1c5f44e63b3ca1115d268454731735f.jpg", "pendant": "", "uname": "战斗型文艺面具", "current_level": 6, "vipStatus": 0, "is_senior_member": 0, "fans_detail": "", "user_sailing": {"id": 50973, "name": "无期迷途", "image": "https://i0.hdslb.com/bfs/garb/item/cb148bcf4959302104d991dc3bd7b5d0aadc6c1d.png", "jump_url": "https://www.bilibili.com/h5/mall/equity-link/collect-home?item_id=50973&isdiy=0&part=card_bg&from=reply&f_source=garb&vmid=12050425&native.theme=1&navhide=1", "fan": {"is_fan": 1, "number": 1518, "color": "#673683", "name": "无期迷途", "num_desc": "001518", "num_prefix": "NO.", "color_format": {"start_point": "0,0", "end_point": "0,100", "colors": ["#673683FF", "#673683FF"], "gradients": [0, 100]}}, "type": "suit"}, "message": "大香老师可能真的是单纯想打造一支顶级乐队，而且她绝对对自己之前干的出生事情心里没有一点逼数在里面，成员不好直接抛弃，好想看大祥老师被mygo这条破船拷打啊（狂喜）", "ctime": "2023-09-15 00:23:50", "like": 7, "pictures": [], "replies": [{"avatar": "https://i2.hdslb.com/bfs/face/e545557a09817e1456881cfeb28d07dafca1f13b.jpg", "uname": "此叶无名", "current_level": 6, "vipStatus": 0, "is_senior_member": 0, "message": "我也好想看组银河战舰打团打输后掉眼泪的大祥老师[脱单doge]", "ctime": "2023-09-15 00:35:16", "like": 0}], "sub_reply_entry_text": "共1条回复", "rcount": 1}, {"rpid": 187568642720, "avatar": "http://i1.hdslb.com/bfs/face/8ff9ae60f389e1e3342e4bf3d58d7df2e9b6b353.jpg", "pendant": "https://i1.hdslb.com/bfs/garb/item/0c8e7d627a35c378b757f39419889ef1fcc0ed9b.png", "uname": "躯机主教", "current_level": 6, "vipStatus": 1, "is_senior_member": 0, "fans_detail": "", "user_sailing": {"id": 2006, "name": "明日方舟", "image": "https://i0.hdslb.com/bfs/garb/item/a1875a74a516f0da31fd94b6112e5e143f9f6076.png", "jump_url": "https://www.bilibili.com/h5/mall/equity-link/collect-home?item_id=2006&isdiy=0&part=card_bg&from=reply&f_source=garb&vmid=350231782&native.theme=1&navhide=1", "fan": {"is_fan": 1, "number": 134844, "color": "#006cff", "name": "明日方舟", "num_desc": "134844", "num_prefix": "NO.", "color_format": {"start_point": "0,0", "end_point": "0,100", "colors": ["#006cffFF", "#006cffFF"], "gradients": [0, 100]}}, "type": "suit"}, "message": "你让月薪3000的和这些大小姐玩什么？你有时间吗，不打工你买得起乐器嘛，你想让她们可怜你吗？大小姐变成月薪3000你甘心吗？不理解的如果你是祥子可能就理解了吧", "ctime": "2023-09-26 18:04:55", "like": 17, "pictures": [], "replies": [{"avatar": "http://i1.hdslb.com/bfs/face/9f7309e5b18b42feca935754e7b931bd376d18e8.jpg", "uname": "黑白con", "current_level": 3, "vipStatus": 0, "is_senior_member": 0, "message": "你这个说法显然是不对的，祥子遭遇很惨是事实，玩不起乐队也能理解，大家都能和她共情。但是她对于前任乐队成员的态度可就不是“理所当然”的了，不理解的也是这一点。这方面百分之百是祥子自己的问题，她可能是不想让人知道她家的情况，或者是不想被人“高高在上”的同情，或者是她想要和过去的自己告别，但无论如何那都是她自己的想法，一声不吭的突然切割，不玩乐队了朋友都没得做，她的行为就和她说素世的那句“你这个人只想着自己呢”完美契合。", "ctime": "2023-09-27 15:23:24", "like": 7}, {"avatar": "http://i1.hdslb.com/bfs/face/8ff9ae60f389e1e3342e4bf3d58d7df2e9b6b353.jpg", "uname": "躯机主教", "current_level": 6, "vipStatus": 1, "is_senior_member": 0, "message": "回复 @黑白con :你也和这句话很契合", "ctime": "2023-09-27 17:02:13", "like": 0}, {"avatar": "http://i0.hdslb.com/bfs/face/b0d4640c49ef04f630b103edbec1a277b912fbe1.jpg", "uname": "cv药丸千岁", "current_level": 6, "vipStatus": 1, "is_senior_member": 0, "message": "没多少人能像大祥老师一般坚强的。。一半咬牙坚持，一半不是摆了就是跳了", "ctime": "2023-09-27 10:59:47", "like": 0}], "sub_reply_entry_text": "共11条回复", "rcount": 11}], "top_replies": []}