{"errno": 0, "totalPage": 4, "replies": [{"avatar": "https://i2.hdslb.com/bfs/face/a28b3b76a12f0cf9291ba929c32ee4428ca7d460.jpg", "uname": "午夜苏打_Official", "current_level": 6, "vipStatus": 1, "is_senior_member": 0, "message": "传达搬家了是骗soyo不要继续纠缠自己，而她实际上也确实搬家了，但不希望其他人知道（包括睦）", "ctime": "2023-09-23 15:09:45", "like": 5}, {"avatar": "https://i2.hdslb.com/bfs/face/a28b3b76a12f0cf9291ba929c32ee4428ca7d460.jpg", "uname": "午夜苏打_Official", "current_level": 6, "vipStatus": 1, "is_senior_member": 0, "message": "回复 @午夜苏打_Official :后者的搬家指搬进很差的房子&amp;家庭出现变故", "ctime": "2023-09-23 15:11:17", "like": 0}, {"avatar": "http://i1.hdslb.com/bfs/face/3f337c299b0ca5b5c078aad52f6970c3773b04b1.jpg", "uname": "剩飯處理騎士團團長", "current_level": 6, "vipStatus": 0, "is_senior_member": 0, "message": "回复 @午夜苏打_Official : 連睦也瞞著就說得通了。<br>之前我想說睦是知曉一切的", "ctime": "2023-09-23 15:28:35", "like": 3}, {"avatar": "https://i2.hdslb.com/bfs/face/754bd1816595c6f1b4c4b3f48fcb9b519cd6bf9b.jpg", "uname": "绯夜艾迪兰斯", "current_level": 6, "vipStatus": 1, "is_senior_member": 0, "message": "要多看后面睦祥互动，不剧透", "ctime": "2023-09-23 15:40:04", "like": 0}]}