{"errno": 0, "totalPage": 3, "replies": [{"avatar": "https://i0.hdslb.com/bfs/face/fbf76e4d7c395f46c435f2480e7cd76242018b61.jpg", "uname": "彼方酱-", "current_level": 6, "vipStatus": 1, "is_senior_member": 1, "message": "花露水[保卫萝卜_白眼]", "ctime": "2023-09-07 23:49:03", "like": 0}, {"avatar": "https://i1.hdslb.com/bfs/face/9083c4dfbff508d8376e94e5c042d1b2be7f0592.jpg", "uname": "口袋有只utena", "current_level": 5, "vipStatus": 0, "is_senior_member": 0, "message": "原神", "ctime": "2023-09-08 00:27:44", "like": 0}, {"avatar": "https://i0.hdslb.com/bfs/face/e14a10c273682b37e15a1c10b6481008f07a78e5.jpg", "uname": "奇迹与幸运的黑发旅人", "current_level": 6, "vipStatus": 0, "is_senior_member": 0, "message": "棍子，当头来一下，醒来不是周四就再来一下", "ctime": "2023-09-08 00:33:48", "like": 0}]}