{"errno": 0, "totalPage": 33, "all_count": 1277, "replies": [{"rpid": 186892467056, "avatar": "http://i1.hdslb.com/bfs/face/757ddcccc16cd41f71149d7e6be06074329d497b.jpg", "pendant": "", "uname": "彭磊1", "current_level": 6, "vipStatus": 1, "is_senior_member": 0, "fans_detail": {"uid": 32422147, "medal_id": 728971, "medal_name": "迷子A", "score": 0, "level": 9, "intimacy": 0, "master_status": 0, "is_receive": 0, "medal_color": 866040552, "medal_color_end": 866040552, "medal_color_border": 782877673, "medal_color_name": 4283924408, "medal_color_level": 4288327890, "guard_level": 0, "guard_icon": "", "honor_icon": "", "medal_level_bg_color": 16777215}, "user_sailing": "", "message": "来了", "ctime": "2023-09-21 22:00:47", "like": 0, "pictures": [], "replies": [], "sub_reply_entry_text": "", "rcount": 0}, {"rpid": 186892460576, "avatar": "https://i1.hdslb.com/bfs/face/9ad6c711e785d29237eccff4247fc8f1c0971897.jpg", "pendant": "", "uname": "b站露lu", "current_level": 5, "vipStatus": 0, "is_senior_member": 0, "fans_detail": "", "user_sailing": "", "message": "来了", "ctime": "2023-09-21 22:00:39", "like": 0, "pictures": [], "replies": [], "sub_reply_entry_text": "", "rcount": 0}, {"rpid": 186892447712, "avatar": "https://i1.hdslb.com/bfs/face/3338e306f9c328035794e848e38cdb1257b9a32b.jpg", "pendant": "", "uname": "酥岁", "current_level": 5, "vipStatus": 0, "is_senior_member": 0, "fans_detail": "", "user_sailing": "", "message": "来了", "ctime": "2023-09-21 22:00:22", "like": 0, "pictures": [], "replies": [], "sub_reply_entry_text": "", "rcount": 0}, {"rpid": 186892445376, "avatar": "https://i1.hdslb.com/bfs/face/f20b42fb0c6b58d367669245062c88480585fcea.jpg", "pendant": "https://i1.hdslb.com/bfs/garb/item/20c07ded13498a5b12db99660c766ddd92ecfe31.png", "uname": "改个名字总重复怎么办", "current_level": 5, "vipStatus": 0, "is_senior_member": 0, "fans_detail": {"uid": 60108892, "medal_id": 728971, "medal_name": "迷子A", "score": 0, "level": 6, "intimacy": 0, "master_status": 0, "is_receive": 0, "medal_color": 866040552, "medal_color_end": 866040552, "medal_color_border": 782877673, "medal_color_name": 4283924408, "medal_color_level": 4288327890, "guard_level": 0, "guard_icon": "", "honor_icon": "", "medal_level_bg_color": 16777215}, "user_sailing": {"id": 1705928478001, "name": "蔚蓝档案", "image": "https://i0.hdslb.com/bfs/baselabs/op/8f873cbc5953808a47be999976b6a7152f829825e7f01617f76bc563e9e83d9c.png", "jump_url": "https://www.bilibili.com/h5/mall/equity-link/collect-home?item_id=1705928478001&isdiy=0&part=card_bg&from=reply&f_source=garb&vmid=60108892&native.theme=1&navhide=1", "fan": {"is_fan": 1, "number": 12278, "color": "#3DC5EC", "name": "蔚蓝档案", "num_desc": "012278", "num_prefix": "NO.", "color_format": {"start_point": "0,0", "end_point": "0,100", "colors": ["#3DC5ECFF", "#3DC5ECFF"], "gradients": [0, 100]}}, "type": "suit"}, "message": "来了", "ctime": "2023-09-21 22:00:19", "like": 0, "pictures": [], "replies": [], "sub_reply_entry_text": "", "rcount": 0}, {"rpid": 186892396128, "avatar": "https://i2.hdslb.com/bfs/face/fdbd8b8e986b95f26728447675adcc39823b4079.jpg", "pendant": "https://i2.hdslb.com/bfs/garb/item/488870931b1bba66da36d22848f0720480d3d79a.png", "uname": "穗状星序", "current_level": 6, "vipStatus": 1, "is_senior_member": 0, "fans_detail": {"uid": 1477811, "medal_id": 728971, "medal_name": "迷子A", "score": 0, "level": 6, "intimacy": 0, "master_status": 0, "is_receive": 0, "medal_color": 866040552, "medal_color_end": 866040552, "medal_color_border": 782877673, "medal_color_name": 4283924408, "medal_color_level": 4288327890, "guard_level": 0, "guard_icon": "", "honor_icon": "", "medal_level_bg_color": 16777215}, "user_sailing": {"id": 49389, "name": "提摩西小队第二弹", "image": "https://i0.hdslb.com/bfs/garb/item/b217e3fec5e1e88a4eae4ccab4994baf89794c3a.png", "jump_url": "https://www.bilibili.com/h5/mall/equity-link/collect-home?item_id=49389&isdiy=0&part=card_bg&from=reply&f_source=garb&vmid=1477811&native.theme=1&navhide=1", "fan": {"is_fan": 1, "number": 3796, "color": "#ca7b2d", "name": "提摩西小队第二弹", "num_desc": "003796", "num_prefix": "NO.", "color_format": {"start_point": "0,0", "end_point": "0,100", "colors": ["#ca7b2dFF", "#ca7b2dFF"], "gradients": [0, 100]}}, "type": "suit"}, "message": "来了", "ctime": "2023-09-21 22:00:18", "like": 0, "pictures": [], "replies": [], "sub_reply_entry_text": "", "rcount": 0}, {"rpid": 187085529360, "avatar": "https://i0.hdslb.com/bfs/face/39e77cb53ab45c87b4c841e1cefef4dbec194778.jpg", "pendant": "", "uname": "OkusawaMisakii", "current_level": 5, "vipStatus": 0, "is_senior_member": 0, "fans_detail": {"uid": 407471319, "medal_id": 728971, "medal_name": "迷子A", "score": 0, "level": 12, "intimacy": 0, "master_status": 0, "is_receive": 0, "medal_color": 866040552, "medal_color_end": 866040552, "medal_color_border": 782877673, "medal_color_name": 4283924408, "medal_color_level": 4288327890, "guard_level": 0, "guard_icon": "", "honor_icon": "", "medal_level_bg_color": 16777215}, "user_sailing": {"id": 67807, "name": "BanGDream！", "image": "https://i0.hdslb.com/bfs/garb/item/bbc13f949040bce6a154d01f9179e8580642455e.png", "jump_url": "https://www.bilibili.com/h5/mall/equity-link/collect-home?item_id=67807&isdiy=0&part=card_bg&from=reply&f_source=garb&vmid=407471319&native.theme=1&navhide=1", "fan": {"is_fan": 1, "number": 8205, "color": "#F67E95", "name": "BanGDream", "num_desc": "008205", "num_prefix": "NO.", "color_format": {"start_point": "0,0", "end_point": "0,100", "colors": ["#F67E95FF", "#F67E95FF"], "gradients": [0, 100]}}, "type": "suit"}, "message": "溜", "ctime": "2023-09-23 10:37:08", "like": 0, "pictures": [], "replies": [], "sub_reply_entry_text": "", "rcount": 0}], "top_replies": []}