{"errno": 0, "totalPage": 5, "replies": [{"avatar": "https://i0.hdslb.com/bfs/face/8ae7257ce7aa96e7002894b419de791928b5f8ee.jpg", "uname": "立希单推人", "current_level": 6, "vipStatus": 0, "is_senior_member": 0, "message": "soyo固然很不对，但伤害她要有个度。凡事做事留一线才是正常节奏，当你一点都不留底线的时候，一般都不太正常了。", "ctime": "2023-09-24 09:45:48", "like": 3}, {"avatar": "https://i1.hdslb.com/bfs/face/9d1073380b784b67f09efb9da13f3b29e33ade92.jpg", "uname": "影名胧月", "current_level": 6, "vipStatus": 1, "is_senior_member": 0, "message": "主要是soyo说的话每一句都精准踩雷……给本来还能维持一下情面的祥子踩爆了。", "ctime": "2023-09-24 19:49:06", "like": 6}, {"avatar": "https://i0.hdslb.com/bfs/face/member/noface.jpg", "uname": "笛卡尔的自然之光", "current_level": 3, "vipStatus": 0, "is_senior_member": 0, "message": "回复 @影名胧月 : 两个人都快被逼疯了，毕竟一个天天堵门一个天天被堵门", "ctime": "2023-09-24 22:32:39", "like": 3}, {"avatar": "https://i0.hdslb.com/bfs/face/8ae7257ce7aa96e7002894b419de791928b5f8ee.jpg", "uname": "立希单推人", "current_level": 6, "vipStatus": 0, "is_senior_member": 0, "message": "回复 @影名胧月 :反正一个崩溃边缘的人对重女确实没好脸色，但事后回归正常，祥子就会明白他有多狠，soyo的尾随也有多入魔了", "ctime": "2023-09-25 00:20:15", "like": 2}, {"avatar": "https://i1.hdslb.com/bfs/face/9d1073380b784b67f09efb9da13f3b29e33ade92.jpg", "uname": "影名胧月", "current_level": 6, "vipStatus": 1, "is_senior_member": 0, "message": "回复 @RED__Comet : mygo主打一个人人都有问题，但是真正分锅的话倒也不至于那么严重。以上帝视角去评判她们是没有意义的，因为这就是青春期迷茫的少女们摸索着试错然后迈向前方的故事啊。", "ctime": "2023-09-25 10:04:18", "like": 2}]}