{"errno": 0, "totalPage": 5, "replies": [{"avatar": "https://i1.hdslb.com/bfs/face/91183a6c5fe9670ffc9316f335138b1ddfb931e5.jpg", "uname": "乱雨唯", "current_level": 6, "vipStatus": 0, "is_senior_member": 0, "message": "13集", "ctime": "2023-08-14 23:13:49", "like": 0}, {"avatar": "https://i0.hdslb.com/bfs/face/c6829b7b64c992341e78daea5485cbf47aa56f63.jpg", "uname": "超高速能猫", "current_level": 6, "vipStatus": 0, "is_senior_member": 0, "message": "一共13集，现在最新就第九集", "ctime": "2023-08-14 23:14:14", "like": 0}, {"avatar": "https://i2.hdslb.com/bfs/face/887ff7beca4c1b4c391a25129490d4688d9ddddf.webp", "uname": "超知恵の海爷", "current_level": 6, "vipStatus": 0, "is_senior_member": 0, "message": "回复 @乱雨唯 :那后面官方还会投稿吗？(*°▽°*)八(*°▽°*)♪", "ctime": "2023-08-14 23:16:15", "like": 0}, {"avatar": "https://i2.hdslb.com/bfs/face/887ff7beca4c1b4c391a25129490d4688d9ddddf.webp", "uname": "超知恵の海爷", "current_level": 6, "vipStatus": 0, "is_senior_member": 0, "message": "回复 @司夜阿 :哦哦 谢谢大佬", "ctime": "2023-08-14 23:16:30", "like": 0}, {"avatar": "http://i2.hdslb.com/bfs/face/08dc27b258f81a4405a2ba51f263bd708800a0af.jpg", "uname": "泠鸢ysaou", "current_level": 5, "vipStatus": 0, "is_senior_member": 0, "message": "回复 @超知恵の海爷 :有限定时间的，19号晚上11点就结束了，官方应该会把这几集删了吧", "ctime": "2023-08-14 23:19:26", "like": 0}]}