{"errno": 0, "totalPage": 54, "replies": [{"avatar": "https://i2.hdslb.com/bfs/face/1496caccaea826e53d1562e6b3d839cc9b5182f2.jpg", "uname": "资深土木天师", "current_level": 5, "vipStatus": 1, "is_senior_member": 0, "message": "回复 @Ma_ko_to_ : 不能这么想啊兄弟，要是MYGO就单纯玩玩还怎么对邦，这俩完全没交集啊，对不上啊[笑哭]<br>所以必须炸雷，必须对邦，不对邦谁看邦邦啊[doge]", "ctime": "2023-09-14 23:18:48", "like": 1}, {"avatar": "https://i0.hdslb.com/bfs/face/9a36e75de647095b34eca77ee3b158953207b207.webp", "uname": "7号防腐剂", "current_level": 6, "vipStatus": 0, "is_senior_member": 0, "message": "牛，这都能撕战力，跟疯狗一样见人就咬，别不懂装懂了[Muse Dash_我不理解]", "ctime": "2023-09-14 23:53:44", "like": 5}, {"avatar": "https://i2.hdslb.com/bfs/face/64527dbb5dbe3880fa0d67a9d8f49acd4b8ff756.jpg", "uname": "流萤的橡木蛋糕", "current_level": 5, "vipStatus": 0, "is_senior_member": 0, "message": "回复 @-希儿希儿希 :不过乐队虽然实力很重要，但是最后看的还是名气比拼，soyo家里面应该不能宣发不了多少，但是睦头可以啊，睦头一看心也不在母鸡卡，说不定后面为了soyo让她爸妈来明星宣发", "ctime": "2023-09-15 00:36:18", "like": 0}, {"avatar": "https://i1.hdslb.com/bfs/face/219e6a58d6b39600040849aa7014b50b27379996.jpg", "uname": "随风飘扬的叶某", "current_level": 5, "vipStatus": 1, "is_senior_member": 0, "message": "扯战力，我只能说电竞看多了", "ctime": "2023-09-15 00:53:01", "like": 2}, {"avatar": "https://i2.hdslb.com/bfs/face/8a9aa69d0324850ade1f4acc50b741d45df9d80f.jpg", "uname": "花寄橘", "current_level": 6, "vipStatus": 1, "is_senior_member": 0, "message": "回复 @Ma_ko_to_ :你看下一篇谁吃瘪就完事了[吃瓜]，全神班又如何，在mygo动画里面输给mygo也有可能", "ctime": "2023-09-15 01:03:59", "like": 0}, {"avatar": "http://i1.hdslb.com/bfs/face/51be7d79548726bd6efce709076ae3ed8b460a8d.jpg", "uname": "時生トキオ", "current_level": 5, "vipStatus": 1, "is_senior_member": 0, "message": "回复 @天廻の龍 :你别的我都不说，你就这句比kkr差也不会差太多，我直接把你打成☁️，你是真不知道kkr有多有钱？她家可以把一个游乐场买了就为了让kkr玩一天[热]，soyo妈有这1/10的水平？", "ctime": "2023-09-15 01:18:17", "like": 2}, {"avatar": "https://i1.hdslb.com/bfs/face/7edd56e907fdf130b67e1059077ecc6dcc104db2.jpg", "uname": "Ma_ko_to_", "current_level": 5, "vipStatus": 0, "is_senior_member": 0, "message": "回复 @花寄橘 :不是，首先mygo动画已经完结了，下一部邦邦叫ave mujica不叫mygo，至少这一点弄清楚。而且am不受点打击谁还看啊，你拿这点来搞对立是吧？", "ctime": "2023-09-15 01:37:57", "like": 0}, {"avatar": "https://i2.hdslb.com/bfs/face/8a9aa69d0324850ade1f4acc50b741d45df9d80f.jpg", "uname": "花寄橘", "current_level": 6, "vipStatus": 1, "is_senior_member": 0, "message": "回复 @Ma_ko_to_ :谁说mygo完结了，首先它是mygo的续篇，这一点是官方pv上面写着的。其次，你说我搞对立？在动画里面明眼人都看得出来这俩有竞争关系的影子在那，祥子和素世的矛盾为暗线，用得着我搞对立？", "ctime": "2023-09-15 01:43:22", "like": 0}, {"avatar": "http://i2.hdslb.com/bfs/face/1a731df843204f63ec9eeb694229123b3f830d03.jpg", "uname": "贩醉咸鱼人左某", "current_level": 6, "vipStatus": 0, "is_senior_member": 0, "message": "呃，祥子系统性学过编曲啊，时间不够能力也还在；初华家里有岛睦父母都是名人咋可能缺财力……喵梦刚买鼓就被祥子相中了，而且喵梦作为音乐博主也不是纯小白，最后睦这次就是为了祥子入的团，再搞事的可能性很小<br>     其实我没搞懂有啥好比的，热血番撕战力也就算了，偶像番也要撕……", "ctime": "2023-09-15 07:34:02", "like": 1}, {"avatar": "https://i2.hdslb.com/bfs/face/d4c1c0611b2f1ac3195048125ab24242c2f3fa40.jpg", "uname": "吃个耶包", "current_level": 6, "vipStatus": 1, "is_senior_member": 0, "message": "回复 @天廻の龍 :我寻思你单纯夸ano没人说你啊 你自己原评论不就是不考虑实际上来就说mygo随便找的几个人吊打了ave 别人和你说根本吊打不看 然后你就一直在爆典 什么soyo家财力吊打ave所有人和kkr差不多 发言太搞笑了大伙不才来笑你撕战力吗[喜极而泣]", "ctime": "2023-09-15 08:49:29", "like": 3}]}