{"errno": 0, "totalPage": 22, "replies": [{"avatar": "https://i0.hdslb.com/bfs/face/df9fdfa20dc331857066c467beedaa65c214dbe3.jpg", "uname": "AnonSoyo_Tokyo", "current_level": 5, "vipStatus": 1, "is_senior_member": 0, "message": "列车是开往虹咲的[doge]立希杀青去赶另一个片场了", "ctime": "2023-09-15 13:08:43", "like": 36}, {"avatar": "http://i2.hdslb.com/bfs/face/82c1ddabcc36363541c99e1ef12961902a640e31.jpg", "uname": "思考中的快乐", "current_level": 6, "vipStatus": 1, "is_senior_member": 0, "message": "回复 @桐絆普阳 :错误的，rikki不需要挺好萌证明自己，反而是挺好萌需要rikki当背景板来证明自己的含金量", "ctime": "2023-09-15 13:55:15", "like": 44}, {"avatar": "https://i1.hdslb.com/bfs/face/347dc76248bf994b8c17d790bb0f5e1c081b852b.jpg", "uname": "約束_Sunday", "current_level": 6, "vipStatus": 1, "is_senior_member": 0, "message": "rikki得不到挺王称号，何尝不是一种挺（）", "ctime": "2023-09-15 14:04:16", "like": 34}, {"avatar": "https://i0.hdslb.com/bfs/face/ac80c76212af11c98cda75d1c01faa0bfc777a57.jpg", "uname": "olddriver0307", "current_level": 5, "vipStatus": 1, "is_senior_member": 0, "message": "被挺王牛了何尝不是另一种挺[吃瓜]", "ctime": "2023-09-15 14:47:25", "like": 36}, {"avatar": "https://i0.hdslb.com/bfs/face/b4a8c722bd0330c550e11921cc9aa402f34cb808.jpg", "uname": "shiny_ch", "current_level": 6, "vipStatus": 0, "is_senior_member": 0, "message": "回复 @强欲魔女艾姬多娜 :感觉这十个人拉出谁来都能播放皆杀的小曲", "ctime": "2023-09-15 15:01:19", "like": 14}, {"avatar": "https://i2.hdslb.com/bfs/face/f77306d314cda5458ded69d790d7eca7bbfdddb5.webp", "uname": "夜羽子ほや", "current_level": 6, "vipStatus": 1, "is_senior_member": 0, "message": "这不是DD头子吗", "ctime": "2023-09-15 17:00:04", "like": 0}, {"avatar": "https://i1.hdslb.com/bfs/face/ede5e1bada166a60fa943dc04d63d419707aaaf3.jpg", "uname": "猫与箱", "current_level": 5, "vipStatus": 1, "is_senior_member": 0, "message": "回复 @桐絆普阳 : 甜甜圈女士和睦头人这两位重量级还没发力呢[吃瓜]", "ctime": "2023-09-15 17:12:11", "like": 16}, {"avatar": "https://i0.hdslb.com/bfs/face/1d3f1fee7d39380a01edd4e33860f227ab6b443f.jpg", "uname": "谁家的脆脆鲨呀", "current_level": 5, "vipStatus": 0, "is_senior_member": 0, "message": "难绷", "ctime": "2023-09-15 17:21:46", "like": 0}, {"avatar": "http://i0.hdslb.com/bfs/face/42916385509db4bf2054a56b92bbad3cf60e021c.jpg", "uname": "御坂7690", "current_level": 6, "vipStatus": 1, "is_senior_member": 0, "message": "没用的，算上甜甜圈女士这十一人全部都有资格竞争挺王[吃瓜][吃瓜][吃瓜]", "ctime": "2023-09-15 19:48:25", "like": 16}, {"avatar": "https://i0.hdslb.com/bfs/face/e99ca06e5c746978587c8ccb8db34613485d1720.jpg", "uname": "TheRainbowO_A", "current_level": 6, "vipStatus": 1, "is_senior_member": 1, "message": "回复 @桐絆普阳 : [妙啊]暗Ri剑魔好像明年要先过睦瓜星灵这一关力~", "ctime": "2023-09-16 08:14:08", "like": 8}]}