{"errno": 0, "totalPage": 17, "replies": [{"avatar": "https://i2.hdslb.com/bfs/face/f54c4e492129379dc7fea349a9c580d732f2ac52.jpg", "uname": "敕妖墨笔", "current_level": 6, "vipStatus": 0, "is_senior_member": 0, "message": "越想越感觉有可能，不然祥子拦灯的那一幕当时看起来有点突兀。现在已知两个团剧本是一起写的，很有可能是为了灯拦祥子做铺垫", "ctime": "2023-09-15 00:02:17", "like": 187}, {"avatar": "https://i1.hdslb.com/bfs/face/8e6320a90045b7da342ac559a22217e25039204d.jpg", "uname": "戴安娜大魔王", "current_level": 6, "vipStatus": 0, "is_senior_member": 0, "message": "woc，真中了回来刀了你", "ctime": "2023-09-15 00:57:58", "like": 30}, {"avatar": "https://i0.hdslb.com/bfs/face/e3d7d418e1dc6e82090e2aa0d5b02d7df9502321.jpg", "uname": "飞翔的呆呆狗", "current_level": 6, "vipStatus": 1, "is_senior_member": 0, "message": "美少女乐队动画真的能这样子写吗？这已经是观众都接不住的沉重了[笑哭]", "ctime": "2023-09-15 01:49:22", "like": 130}, {"avatar": "https://i0.hdslb.com/bfs/face/753c0e081ca57ce9ea40a80298c801df7a532365.jpg", "uname": "TwoFlycats", "current_level": 6, "vipStatus": 0, "is_senior_member": 0, "message": "真这么演，大家就不是看乐子了[笑哭]现在还是属于背景比较沉重，这样的话就直接剧情发展全部变味，究极苦情大剧", "ctime": "2023-09-15 10:18:44", "like": 23}, {"avatar": "https://i0.hdslb.com/bfs/face/f98f522991dba361b7e410be0d99ec86a4afd751.jpg", "uname": "Ande-Califor", "current_level": 6, "vipStatus": 1, "is_senior_member": 0, "message": "回复 @无厌丶呆呆狗 :你想当时为什么祥子会觉得灯要轻生？<br>她会不会见过？<br>mygo_ave早就不是什么传统的美少女乐队番了", "ctime": "2023-09-15 10:31:40", "like": 122}, {"avatar": "https://i2.hdslb.com/bfs/face/f54c4e492129379dc7fea349a9c580d732f2ac52.jpg", "uname": "敕妖墨笔", "current_level": 6, "vipStatus": 0, "is_senior_member": 0, "message": "回复 @TwoFlycats :就是一个猜测，可能是类似的场景，但没有这么沉重。<br>我现在感觉母鸡卡是不会从其他人开始崩的，不然故事实在太沉重了。我现在的猜测是母鸡卡其他人慢慢发现祥子极力隐瞒的现状，祥子的遮羞布被彻底撕碎跑路到桥上遇到灯的互相救赎的故事", "ctime": "2023-09-15 15:01:25", "like": 27}, {"avatar": "https://i2.hdslb.com/bfs/face/4324143e75f4d304b2e97cb1ac3bc41d30824191.jpg", "uname": "谷启夏", "current_level": 6, "vipStatus": 0, "is_senior_member": 0, "message": "我也觉得，ave已经是唯一的心灵支柱了，这要崩了就彻底崩了", "ctime": "2023-09-15 15:17:43", "like": 9}, {"avatar": "http://i0.hdslb.com/bfs/face/5e2be44e90fefee47d48c6ac8edea29bcfafc4c8.jpg", "uname": "总裁下放", "current_level": 6, "vipStatus": 1, "is_senior_member": 0, "message": "回复 @谷启夏 :这都不止是心灵支柱了，也是现实支柱，祥子孤注一掷用上全部人脉与自己的心血做出的最后一博，也是她对命运的反抗，用睦的话来讲，感觉Saki像要坏掉了一样", "ctime": "2023-09-15 15:22:51", "like": 59}, {"avatar": "https://i1.hdslb.com/bfs/face/5c5d0ccca944ee268adbc1e17a54afc6af516cc2.jpg", "uname": "A4紙君", "current_level": 5, "vipStatus": 1, "is_senior_member": 0, "message": "但是由木頭人拯救祥子比較好。為了保護心愛的姐姐，木頭人捨棄了以往的懦弱，勇敢地站出來保護祥子。SOYO是過去的女人，燈也只是愛音的女人，接下來是姐妹百合的大時代。", "ctime": "2023-09-15 19:59:32", "like": 19}, {"avatar": "https://i2.hdslb.com/bfs/face/aa74454a41436464a65d40bd08b5d1cd5c8dfe27.jpg", "uname": "萝北_luobei", "current_level": 6, "vipStatus": 1, "is_senior_member": 0, "message": "回复 @A4紙君 :姐妹说重铸荣光！", "ctime": "2023-09-16 02:15:48", "like": 4}]}