{"errno": 0, "totalPage": 27, "replies": [{"avatar": "https://i2.hdslb.com/bfs/face/6a0892affd744d89f6e3c9f1eecd81c711ce45e2.jpg", "uname": "我家住801室", "current_level": 6, "vipStatus": 1, "is_senior_member": 1, "message": "回复 @烤蘑菇不能没有葱 :快让我看avemujica第一集[委屈]（下跪）我什么都会做的[委屈]", "ctime": "2023-09-15 16:51:25", "like": 34}, {"avatar": "https://i2.hdslb.com/bfs/face/25cc22712befa88bc6a29d0122c4a8c1e8adde22.jpg", "uname": "七骑破晓", "current_level": 6, "vipStatus": 0, "is_senior_member": 1, "message": "回复 @千面墨 :经纪公司不管报销是吧？", "ctime": "2023-09-15 21:53:23", "like": 0}, {"avatar": "http://i2.hdslb.com/bfs/face/7027b300b746787da2de9f4647a2d3f11afda40e.jpg", "uname": "雨卍林", "current_level": 6, "vipStatus": 1, "is_senior_member": 0, "message": "回复 @小智Sekiar :确实，在动画前三集里，睦来找祥子说soyo想见她，祥子让睦跟soyo说她搬家了，潜台词就是当时祥子还住在原来的大house里，可能是春日影之后祥子才下定决心反抗家里的吧。", "ctime": "2023-09-15 23:02:26", "like": 47}, {"avatar": "https://i2.hdslb.com/bfs/face/5e5fc7cc6cd160db73e6c14f6071a7a7f63d2b7f.jpg", "uname": "Uni0-0", "current_level": 6, "vipStatus": 1, "is_senior_member": 0, "message": "回复 @雨卍林 :我嘞豆啊 还真是 原来的大豪斯应该还在", "ctime": "2023-09-16 03:13:00", "like": 3}, {"avatar": "https://i1.hdslb.com/bfs/face/cdffd138ebf40f72874f4c47a349c9d2992af223.jpg", "uname": "从来没觉得长大开心过", "current_level": 6, "vipStatus": 0, "is_senior_member": 0, "message": "回复 @Uni0-0 :怎么可能啊", "ctime": "2023-09-16 03:30:43", "like": 0}, {"avatar": "https://i0.hdslb.com/bfs/face/e99ca06e5c746978587c8ccb8db34613485d1720.jpg", "uname": "TheRainbowO_A", "current_level": 6, "vipStatus": 1, "is_senior_member": 1, "message": "回复 @柏鵺_MELODY :初华是最有可能知道点啥的 因为忘记一切那一晚谁也不值得祥老师在初华的温暖怀抱里都唠了点啥[捂眼][星宫汐_贴贴]", "ctime": "2023-09-16 08:02:21", "like": 11}, {"avatar": "https://i0.hdslb.com/bfs/face/8e12bc9e68f13d47d5c82696daa123f529bcceaa.jpg", "uname": "夏日向阳子", "current_level": 6, "vipStatus": 0, "is_senior_member": 0, "message": "我以为她要去上夜班", "ctime": "2023-09-16 11:44:34", "like": 0}, {"avatar": "https://i0.hdslb.com/bfs/face/58e6abfc79402bcd6024fe99bf59e57504369923.jpg", "uname": "柏鵺_MELODY", "current_level": 6, "vipStatus": 0, "is_senior_member": 0, "message": "回复 @TheRainbowO_A : 看最后一集初华想要和祥子一起回家 祥子拒绝了且支开所有人他们去坐出租车 也就说祥子没初华说过自己的事情 就8集不是初华和祥子在公园见面 说啊我们一年多没见了 谢谢你跟我发信息啊打电话什么的就那晚他们其实没有见面就是煲电话粥 初华问道祥子乐队怎么样 祥子就黑脸了说不要提那个乐队 说明那天打电话粥祥子也就更初华说了点别的缓解一下情绪 乐队什么的家里状况他都没和初华讲过  第二季肯定要给大家发现祥子家破产的事情 所以我现在立马就要看第二季！！！！！", "ctime": "2023-09-16 12:32:49", "like": 19}, {"avatar": "https://i2.hdslb.com/bfs/face/5e5fc7cc6cd160db73e6c14f6071a7a7f63d2b7f.jpg", "uname": "Uni0-0", "current_level": 6, "vipStatus": 1, "is_senior_member": 0, "message": "回复 @血族就这么没了 :你看我回复的那个人说的 祥子有一次说是 可以告诉soyo我搬家了吗 应该是说明原来的大豪斯还在吧", "ctime": "2023-09-16 13:24:57", "like": 3}, {"avatar": "https://i0.hdslb.com/bfs/face/9f6eea86645f9779bd8269ab0e2752aefafed529.jpg", "uname": "宇宙无敌大帅比bbbbb", "current_level": 5, "vipStatus": 0, "is_senior_member": 0, "message": "是跟crychic的对比，也是跟mygo的对比", "ctime": "2023-09-16 13:26:21", "like": 0}]}