{"errno": 0, "totalPage": 53, "replies": [{"avatar": "https://i1.hdslb.com/bfs/face/5ab9461eb1c5f44e63b3ca1115d268454731735f.jpg", "uname": "战斗型文艺面具", "current_level": 6, "vipStatus": 0, "is_senior_member": 0, "message": "回复 @Rokakaaa :怎么说呢，我刚看完道诡异仙，来做个类比:<br>李火旺如果单看外在，他不仅要颜值有颜值，要家境有家境，还能打架，战斗力爆表，妥妥玛丽苏男主，可惜他是个癫子，他从来没有想害过任何一个人，可确确实实就是挟持了一个无辜女孩，就是杀了好几个劫匪，就是拿刀捅了自己女朋友<br>我们以李火旺的视角，他当然是无奈之举，但是在女友杨娜的老爹看来，这不就是个疯子吗？你都捅我女儿了，我凭什么要理解你？<br><br>大香老师也是一样，你的确年龄小，你的确还不成熟，你的确有苦衷，但错就是错，你谜语人不好好讲清楚 不管怎么样这责任就在于你， 你现在看了祥子的视角，才知道她是出于自尊心，是家里遭到了变故，那其他人怎么知道？路人怎么知道？别人眼里，你祥子就是突然一踢四还上压力伤关心你的朋友的心不是吗？<br><br>这件事情没有必要洗白，还是那句话，错就是错，你们自己都说祥子人设丰满，那么必然祥子是有好有坏，我觉得可以喜欢，但必定是像素世那样，被狠狠破防了，吃了瘪，才会讨人喜欢", "ctime": "2023-09-16 12:40:15", "like": 5}, {"avatar": "https://i1.hdslb.com/bfs/face/5ab9461eb1c5f44e63b3ca1115d268454731735f.jpg", "uname": "战斗型文艺面具", "current_level": 6, "vipStatus": 0, "is_senior_member": 0, "message": "回复 @Rokakaaa :当然，我不是说要你们去讨厌，只是很多人都急着去洗白祥子，我认为没必要，而应该正视她不完美的地方，承认这就是错事", "ctime": "2023-09-16 12:41:57", "like": 9}, {"avatar": "http://i2.hdslb.com/bfs/face/18835aeab6f49c7e3c456afe3562fbba835bd3c1.jpg", "uname": "wdbbdyhhd", "current_level": 5, "vipStatus": 0, "is_senior_member": 0, "message": "回复 @战斗型文艺面具 :是的，她自己问题有，也有非常不讨人喜欢的地方，我自己喜欢她是因为她的不完美。现在展现出来的形象被骂也是正常的，因为观众和无辜的角色没有义务去包容她。只是之前那个评论说不跟乐队的说原因和组新乐队就是恶心，我觉得这个词有点过重所以反驳了一下，她的行为是符合她性格的，观众从情感上不接受也是正常的。", "ctime": "2023-09-16 15:14:49", "like": 18}, {"avatar": "https://i2.hdslb.com/bfs/face/3bd02baf59a8529123c086a42598b03c9ed9e287.jpg", "uname": "泣舞牵魂", "current_level": 6, "vipStatus": 1, "is_senior_member": 0, "message": "现在不明白为什么要去做客服，为什么不去做音乐相关的兼职，比如音乐家教。这样能保持自己的音乐技能不生疏，而且赚钱应该会比客服多", "ctime": "2023-09-16 18:21:04", "like": 0}, {"avatar": "https://i1.hdslb.com/bfs/face/ad2e4a3b19e83731606cbd49c4ddec9b1b0ac0ff.jpg", "uname": "Pattio", "current_level": 6, "vipStatus": 1, "is_senior_member": 1, "message": "每多看一次祥子老师！就多喜欢多欣赏祥子老师一分！祥子老师是非常有能力的人！", "ctime": "2023-09-16 21:06:26", "like": 1}, {"avatar": "https://i0.hdslb.com/bfs/face/member/noface.jpg", "uname": "推薦一本書", "current_level": 4, "vipStatus": 0, "is_senior_member": 0, "message": "回復 @泣舞牵魂 :在bd 前面幾部，音樂廳老闆娘連房租都湊不出而倒店。", "ctime": "2023-09-16 22:20:04", "like": 4}, {"avatar": "https://i2.hdslb.com/bfs/face/3bd02baf59a8529123c086a42598b03c9ed9e287.jpg", "uname": "泣舞牵魂", "current_level": 6, "vipStatus": 1, "is_senior_member": 0, "message": "回复 @推薦一本書 :这样啊", "ctime": "2023-09-16 22:48:42", "like": 0}, {"avatar": "http://i0.hdslb.com/bfs/face/49d58ebea0878fbfd1d40efd27e0811ea2748b00.jpg", "uname": "无尽之渊2", "current_level": 6, "vipStatus": 1, "is_senior_member": 0, "message": "破产论加大人堕落玩太大了，又是光明堕入黑暗，祥子这种情况直接跳了我都不会意外，抗压真的拉满了", "ctime": "2023-09-16 23:59:29", "like": 15}, {"avatar": "https://i0.hdslb.com/bfs/face/239072d6f59572afd6592f02e171370100962d88.jpg", "uname": "Rokakaaa", "current_level": 6, "vipStatus": 0, "is_senior_member": 0, "message": "回复 @战斗型文艺面具 :不是，根本没人在乎完不完美啊。完美我看什么？你要是给她事后复盘她自己也知道不妥的，但问题是就算代入我们自己，当时能做的那么好吗？我的观点是只要符合动机和人设，符合当时的情绪，就是可以的，没必要好的剧本里挑人物好坏的刺。", "ctime": "2023-09-17 01:36:40", "like": 17}, {"avatar": "https://i0.hdslb.com/bfs/face/4eccb321569dc9b823a237b81d9295c2e64de9e9.jpg", "uname": "星海夜曲", "current_level": 6, "vipStatus": 1, "is_senior_member": 0, "message": "回复 @黑山熊君 :祥子这抗压能力都快赶上佐仓杏子了[笑哭]", "ctime": "2023-09-17 04:29:07", "like": 1}]}