{"errno": 0, "totalPage": 173, "replies": [{"avatar": "https://i2.hdslb.com/bfs/face/abb316c2338d62c233aecd8e5f17dda6358e6974.jpg", "uname": "赤夕V", "current_level": 6, "vipStatus": 0, "is_senior_member": 1, "message": "回复 @花小泉杏是勇者 :mygo是这样的，10集刚播那会儿大伙也说节奏赶，但情绪到位了能让大家沉浸体验剧情后再慢慢消化。第12集有人也说赶，觉得一上来就是live没有日常过渡（比如soyo衣服被剪怎么办）没必要塞Ave部分的内容，不过连着11、12集一起看就完全没问题。<br>这集也差不多，虽然一上来祥子打工我确实直接“啊？”，但看完两遍后觉得也还行，mygo给了很多爆点稀释可能有些奇怪的节奏，也算是一种比较极端的表现方法吧。等到Ave开播了，把mygo和Ave连起来看就是了（我个人更喜欢这种），反正两个团目前是剪不断理还乱的关系，之间的火花肯定能给观众惊喜", "ctime": "2023-09-14 22:44:03", "like": 1}, {"avatar": "https://i2.hdslb.com/bfs/face/42309cfcb4c256210fa9bc87526ac1bb42b1c035.jpg", "uname": "妖刀姬_Offical", "current_level": 6, "vipStatus": 0, "is_senior_member": 0, "message": "回复 @superubbish :可能是的吧，那就能解释祥子黑化又当谜语人的原因了，就是家道中落却难以启齿吧。估计在母鸡卡第一话里就会解释迈狗第一话里的祥子为什么被雨淋湿的跑进来宣布退团了吧", "ctime": "2023-09-14 22:44:09", "like": 0}, {"avatar": "https://i1.hdslb.com/bfs/face/57b6cbb38ff89d7d9b091fabf7053ea82d8eacf6.jpg", "uname": "木咲流年", "current_level": 6, "vipStatus": 0, "is_senior_member": 0, "message": "回复 @原初形态霞龙 : 那是个公园，已经有人实地考据过了，剧情前面还有个祥子走过豪宅的画面明显是故意误导的伏笔", "ctime": "2023-09-14 22:45:48", "like": 2}, {"avatar": "https://i1.hdslb.com/bfs/face/16fb2d016607d45869be9cf27969921654e3e1f3.jpg", "uname": "GWkl", "current_level": 6, "vipStatus": 0, "is_senior_member": 0, "message": "回复 @花小泉杏是勇者 :感觉还是soyo念念不忘crychic想复辟的行为引起祥子的厌恶了  毕竟祥子已经回不到过去了", "ctime": "2023-09-14 22:46:41", "like": 1}, {"avatar": "https://i1.hdslb.com/bfs/face/ae2aa726fd14f5fff714bfe18652cfa1d89cf429.jpg", "uname": "奈眠Iris", "current_level": 5, "vipStatus": 0, "is_senior_member": 0, "message": "想问问祥睦姐妹说的出处在哪啊？听说过很多次但不知道出处", "ctime": "2023-09-14 22:47:55", "like": 0}, {"avatar": "https://i2.hdslb.com/bfs/face/42309cfcb4c256210fa9bc87526ac1bb42b1c035.jpg", "uname": "妖刀姬_Offical", "current_level": 6, "vipStatus": 0, "is_senior_member": 0, "message": "回复 @久保同学请别放过我 : 嗯，之前最担心的就是制作组憋了半天弄了一个很扯淡的理由让祥子当谜语人，搞得之前迈狗经历的那些挫折就全像是个笑话似的，然后大家就一起欢乐的包饺子了。还好制作组没这么干，这个结尾可以说是给出了比较合理的原因了，而且也是一笔带过没有细说，算是给下一季留悬念。唯一觉得困惑的就是这个结尾作为迈狗的结尾有点诡异了点。有种话没说完突然就戛然而止的感觉", "ctime": "2023-09-14 22:49:19", "like": 5}, {"avatar": "https://i0.hdslb.com/bfs/face/2b560dbe4e2b0ea1370a55b3c97422b654596df2.jpg", "uname": "花小泉杏是勇者", "current_level": 5, "vipStatus": 0, "is_senior_member": 0, "message": "回复 @赤夕V :与其说是赶…我觉得是我的疑惑更多了[笑哭]", "ctime": "2023-09-14 22:49:46", "like": 4}, {"avatar": "https://i1.hdslb.com/bfs/face/dce120bb9cbb9371601782d9fece28b912b89f05.jpg", "uname": "瑞树树树树", "current_level": 6, "vipStatus": 0, "is_senior_member": 0, "message": "回复 @shantaoy :那就不是BanGDream It&#39;s MyGO!!!!!了", "ctime": "2023-09-14 22:49:57", "like": 0}, {"avatar": "https://i1.hdslb.com/bfs/face/878fa71b3e4baa5d24ab56dbedd57f52565176bb.jpg", "uname": "信陵亮止", "current_level": 6, "vipStatus": 1, "is_senior_member": 0, "message": "回复 @原初形态霞龙 :惊世一跪的地方是一个国家公园，后面那个白房子被人圣地巡礼确认是厕所（）", "ctime": "2023-09-14 22:51:43", "like": 1}, {"avatar": "https://i0.hdslb.com/bfs/face/2b560dbe4e2b0ea1370a55b3c97422b654596df2.jpg", "uname": "花小泉杏是勇者", "current_level": 5, "vipStatus": 0, "is_senior_member": 0, "message": "回复 @奈眠nemu :我不知道怎么贴链接，你搜一下祥睦远坂姐妹说，应该能搜到。", "ctime": "2023-09-14 22:52:08", "like": 0}]}